[
  {
    "title": "3D Printing Timelapse - 1 meter high",
    "url": "yid-hrv0sDACB7M.jpg"
  },
  {
    "title": "How Do 3D Printers Work?",
    "url": "yid-qoBU0r7pT84.jpg"
  },
  {
    "title": "What is 3D printing?",
    "url": "yid-bcTzyx35odY.jpg"
  },
  {
    "title": "3D Printers | How It's Made",
    "url": "yid-f4RGU2jXQiE.jpg"
  },
  {
    "title": "Creality Ender 3 V2 - 3D Printer - Unbox & Setup",
    "url": "yid-gokN9xNG94U.jpg"
  },
  {
    "title": "How to install CR-Touch on Ender 3 v2 and CR-Touch REVIEW",
    "url": "yid-lN5n7Dy0quk.jpg"
  },
  {
    "title": "21 First Upgrades For Your Ender 3 V2 // Best Mods For Ender 3 V2",
    "url": "yid-JarbS8-R7i4.jpg"
  },
  {
    "title": "Making Furniture with a 3D Printer?! ft. CR-30",
    "url": "yid-iJEq-vBG1Ws.jpg"
  },
  {
    "title": "ANOUK WIPPRECHT",
    "url": "yid-cK02id_3aS8.jpg"
  },
  {
    "title": "Anouk Wipprecht integrates parking sensors into 3D-printed fashion collection",
    "url": "yid-RUOd8uku6Og.jpg"
  },
  {
    "title": "Anouk Wipprecht's Spider Dress",
    "url": "yid-U7dpyphjHAs.jpg"
  },
  {
    "title": "JULIA KOERNER",
    "url": "yid-sjkQpepoi9Y.jpg"
  },
  {
    "title": "Julia Koerner on 3D-printed fashion and Black Panther",
    "url": "yid-aVXo81FMxbE.jpg"
  },
  {
    "title": "Alumni Advice: Julia Koerner",
    "url": "yid-EyEK44WM3WI.jpg"
  },
  {
    "title": "DANIT PELEG",
    "url": "yid-w1oKe8OaPbk.jpg"
  },
  {
    "title": "Why 3D printed fashion is more sustainable and can revolutionize the fashion industry?",
    "url": "yid-o1QXJWlNiv0.jpg"
  },
  {
    "title": "Behind the scenes of the first 3D printed fashion collection",
    "url": "yid-fBK-AKWc5cE.jpg"
  },
  {
    "title": "3D Printed Knife - Will It Cut Paper?",
    "url": "yid--4FBpN_vjoM.jpg"
  },
  {
    "title": "3D Printed BALISONG TRAINER (FreeCAD Design and Printing)",
    "url": "yid-H_9saDVRmSc.jpg"
  },
  {
    "title": "Karambit",
    "url": "yid-xu4L1X-CUR8.jpg"
  },
  {
    "title": "Printing A Dagger On A Resin Printer",
    "url": "yid-J7njc7HciTg.jpg"
  },
  {
    "title": "3D Printed Knives & Tools...",
    "url": "yid-rMJOE9HpTBA.jpg"
  },
  {
    "title": "Eiffel Tower 3D print timelapse",
    "url": "yid-1clUy0ajTdY.jpg"
  },
  {
    "title": "Beautiful MSLA 3D Print Time-lapse",
    "url": "yid-ncUuVMOFGxE.jpg"
  },
  {
    "title": "Insanely Beautiful 3D Printing Time Lapse",
    "url": "yid-LCXjaTNx_vg.jpg"
  },
  {
    "title": "Baby Groot - 3D Printing Time Lapse",
    "url": "yid-m_QhY1aABsE.jpg"
  },
  {
    "title": "9 3D Printing Timelapses / Octolapses On the Creality Ender 3 3D Printer",
    "url": "yid-fNcBXWirC8s.jpg"
  },
  {
    "title": "7 Satisfying 3D Print Time Lapses octolapses Ender 3 Prusa mk3s",
    "url": "yid-yb7sdZTwbuk.jpg"
  },
  {
    "title": "3D Printing TimeLapse episode 8 (Prusa Mk3 octolapse)",
    "url": "yid-aubLuCFIejc.jpg"
  },
  {
    "title": "3D Printing TimeLapses Episode 18! JGAURORA A5 edition octolapse review",
    "url": "yid-hyqRUESYqdE.jpg"
  },
  {
    "title": "3D Printing Fails Compilation - Ender 3 V2",
    "url": "yid-h8USHH3e82Q.jpg"
  },
  {
    "title": "PRINTER FAILS",
    "url": "yid-JGpCGOMgk5g.jpg"
  },
  {
    "title": "3D Printing Fails",
    "url": "yid-ZmS-3Kcti10.jpg"
  },
  {
    "title": "Food 3D Printing",
    "url": "yid-IRsMNXhB5VU.jpg"
  },
  {
    "title": "The Art Of: Dessert - 3D Sugar Printing",
    "url": "yid-fo0HMDzzfFY.jpg"
  },
  {
    "title": "This is what 3D-Printed Food looks like!",
    "url": "yid-M4vjawyh93o.jpg"
  },
  {
    "title": "3D Printing Food",
    "url": "yid-lhOa_eWLJ5o.jpg"
  },
  {
    "title": "Print your BREAKFAST",
    "url": "yid-6rEHNGPibb0.jpg"
  },
  {
    "title": "choc mate 2",
    "url": "yid-5wL3GLEEetI.jpg"
  },
  {
    "title": "Foodini Quick Training: First Print",
    "url": "yid-KFRQ0BEmvIE.jpg"
  },
  {
    "title": "3D Printed Miniatures Finally Amazing?",
    "url": "yid-ThRbiS258IM.jpg"
  },
  {
    "title": "How To Print Resin-Like FDM Minis on $200+ 3D Printers",
    "url": "yid-qDW7g3JOqLA.jpg"
  },
  {
    "title": "The Magic of Printing Resin Miniatures: A Beginner's Guide to Resin 3D Printing",
    "url": "yid-I4bUhsZQkH8.jpg"
  },
  {
    "title": "What if 3D printing was 100x faster? | Joseph DeSimone",
    "url": "yid-ihR9SX7dgRo.jpg"
  },
  {
    "title": "Top 5 Metal 3D Printers 2021",
    "url": "yid-q9-BxLwZXh0.jpg"
  },
  {
    "title": "I 3D Printed a 6000 pound Statue of MYSELF",
    "url": "yid-FaNLkd0rzXk.jpg"
  },
  {
    "title": "Startup Seeks to Print Houses for $0",
    "url": "yid-p_ZbTD-2keo.jpg"
  },
  {
    "title": "3D Printable Waterproof Concrete",
    "url": "yid-6XISEVSTRq4.jpg"
  },
  {
    "title": "Recycle Cardboard into Anything with 3D Printing!",
    "url": "yid-0ItPfhx3ulw.jpg"
  },
  {
    "title": "Lost PLA metal casting",
    "url": "yid-cvi8A2XCK94.jpg"
  },
  {
    "title": "Czinger 21C: the world’s first 3D printed hypercar",
    "url": "yid-OCto6qSjIXw.jpg"
  },
  {
    "title": "The world's largest 3D printed boat built by the largest 3D printer",
    "url": "yid-9U1UbMmNywA.jpg"
  },
  {
    "title": "My Custom 3D Printed Iron Man Suit (An Overview)",
    "url": "yid-lB3M0vLS5Gw.jpg"
  },
  {
    "title": "Project Heartbreaker - Part 1 | Printing the Upper Body",
    "url": "yid--XCPCpknKAk.jpg"
  },
  {
    "title": "Project Heartbreaker - Part 2 | Finishing Printing!",
    "url": "yid-xNsjkp79gGk.jpg"
  },
  {
    "title": "Project Heartbreaker - Part 3 | Is It Complete?",
    "url": "yid-6xp6ciqahJk.jpg"
  }
]