[
  {
    "title": "Why people believe they can’t draw - and how to prove they can | Graham Shaw | TEDxHull",
    "url": "https://www.youtube.com/watch?v=7TXEZ4tP06c",
    "hostname": "www.youtube.com"
  },
  {
    "title": "Solving the Exaggeration with a Checklist (❤️REMEMBER AMPLIFY LIKENESS❤️)",
    "url": "https://www.youtube.com/watch?v=2UESwoOPVOE",
    "hostname": "www.youtube.com"
  },
  {
    "title": "Developing Your Style by Studying the Masters",
    "url": "https://www.youtube.com/watch?v=6P8hos5PL_4",
    "hostname": "www.youtube.com"
  },
  {
    "title": "Caricature Essentials From Start to Finish",
    "url": "https://www.youtube.com/watch?v=EGutjSF8XLs",
    "hostname": "www.youtube.com"
  },
  {
    "title": "Jack Davis, Goin' Back: Remembering UGA Oral History Collection (Encouraged ❤️❤️❤️)",
    "url": "https://www.youtube.com/watch?v=jFbvplpQog8",
    "hostname": "www.youtube.com"
  },
  {
    "title": "Mort Drucker & John Reiner - The NCS Masters Collection",
    "url": "https://www.youtube.com/watch?v=8zNk6-2c75Q",
    "hostname": "www.youtube.com"
  },
  {
    "title": "1987 Mad Magazine's Mort Drucker, Dick Debartolo, Nick Meglin TV intvw",
    "url": "https://www.youtube.com/watch?v=VR4WpgJ7QkE",
    "hostname": "www.youtube.com"
  },
  {
    "title": "Tom Richmond",
    "url": "https://www.youtube.com/watch?v=Vp3fOLl9GVg",
    "hostname": "www.youtube.com"
  },
  {
    "title": "Behind the Scenes of the Goodfelons Splash Page from CLAPTRAP! (Very Informative ❤️)",
    "url": "https://www.youtube.com/watch?v=ekslGlhGG_c",
    "hostname": "www.youtube.com"
  },
  {
    "title": "Albert Einstein Caricature",
    "url": "https://www.youtube.com/watch?v=U3RGzdywZ3E",
    "hostname": "www.youtube.com"
  },
  {
    "title": "Caricature of Al and Peg Bundy",
    "url": "https://www.youtube.com/watch?v=Xs-yoCIFZVw",
    "hostname": "www.youtube.com"
  },
  {
    "title": "How to Draw Caricatures with Tom Richmond",
    "url": "https://www.youtube.com/watch?v=ByLHYNIa42k",
    "hostname": "www.youtube.com"
  },
  {
    "title": "Tom's Studio Tour and Live Caricature Demo",
    "url": "https://www.youtube.com/watch?v=bfSijT9DfUQ",
    "hostname": "www.youtube.com"
  },
  {
    "title": "CLAPTRAP: Ink Along With Tom!",
    "url": "https://www.youtube.com/watch?v=a42ytg-cTrU",
    "hostname": "www.youtube.com"
  },
  {
    "title": "Morena Baccarin Sketch",
    "url": "https://www.youtube.com/watch?v=GjJaH7PP4PM",
    "hostname": "www.youtube.com"
  },
  {
    "title": "The Mad Art of Caricature by Tom Richmond ($24)",
    "url": "https://www.youtube.com/watch?v=QRfNBI4PVa4",
    "hostname": "www.youtube.com"
  },
  {
    "title": "Jack Davis & Nick Meglin",
    "url": "https://www.youtube.com/watch?v=WXzz4GoqlMg",
    "hostname": "www.youtube.com"
  },
  {
    "title": "Steve Bell at 5x15 on political cartoons",
    "url": "https://www.youtube.com/watch?v=TVjAApcjL_A",
    "hostname": "www.youtube.com"
  },
  {
    "title": "HOW TO draw a portrait in Polina Bright signature portrait style",
    "url": "https://www.youtube.com/watch?v=uhYkhuFZywM",
    "hostname": "www.youtube.com"
  },
  {
    "title": "DRAWING PORTRAIT WITH COLORED PENCILS | Try this if you are bored on quarantine",
    "url": "https://www.youtube.com/watch?v=3zfAe3E-frI",
    "hostname": "www.youtube.com"
  },
  {
    "title": "Princess Leia, Alex Raymond Study, Ink and Watercolor",
    "url": "https://www.youtube.com/watch?v=-ZAyu2MZv2Y",
    "hostname": "www.youtube.com"
  },
  {
    "title": "Watercolor VS Gouache Painting (with Grisaille)",
    "url": "https://www.youtube.com/watch?v=MzwnP8AyX9w",
    "hostname": "www.youtube.com"
  },
  {
    "title": "Portfolio Tour & Travel Easel Contents! (❤️)",
    "url": "https://www.youtube.com/watch?v=u-ssyTGKPBM",
    "hostname": "www.youtube.com"
  },
  {
    "title": "UNFAIR Skillshare Nightmare!!",
    "url": "https://www.youtube.com/watch?v=hKNgxgo5f64",
    "hostname": "www.youtube.com"
  },
  {
    "title": "Repretel com Parte de tu Vida",
    "url": "https://www.youtube.com/watch?v=7J89PmH4ySA",
    "hostname": "www.youtube.com"
  },
  {
    "title": "Ecuador",
    "url": "https://www.youtube.com/watch?v=j1EoCn-yHhg",
    "hostname": "www.youtube.com"
  },
  {
    "title": "Neil deGrasse Tyson Caricature",
    "url": "https://www.youtube.com/watch?v=xfLZvSX8L6o",
    "hostname": "www.youtube.com"
  },
  {
    "title": "Live Master Caricature",
    "url": "https://www.youtube.com/watch?v=aZzzAWFlOCs",
    "hostname": "www.youtube.com"
  },
  {
    "title": "Caricature Art of Hector Lopez",
    "url": "https://www.youtube.com/watch?v=-ovSyuSYg84",
    "hostname": "www.youtube.com"
  },
  {
    "title": "Live Event Caricatures By Edd Travers",
    "url": "https://www.youtube.com/watch?v=m_qAsb83kKY",
    "hostname": "www.youtube.com"
  },
  {
    "title": "Eindhoven minicon caricatures",
    "url": "https://www.youtube.com/watch?v=VPn6LkjC0-Q",
    "hostname": "www.youtube.com"
  },
  {
    "title": "Digital caricature sketch time lapse",
    "url": "https://www.youtube.com/watch?v=Ig0tpYRVTEc",
    "hostname": "www.youtube.com"
  },
  {
    "title": "DRAWING FUNNY CARICATURES OF PEOPLE | B3ST REACTIONS [Pt. 1]",
    "url": "https://www.youtube.com/watch?v=zVSaPpn8430",
    "hostname": "www.youtube.com"
  },
  {
    "title": "DRAWING FUNNY CARICATURES OF PEOPLE | B3ST REACTIONS [Pt. 2]",
    "url": "https://www.youtube.com/watch?v=TF3K3bp6vAQ",
    "hostname": "www.youtube.com"
  },
  {
    "title": "Singapore Portrait Caricatures- Adam Chua | Caricaturist.sg",
    "url": "https://www.youtube.com/watch?v=kahHeBmMwEM",
    "hostname": "www.youtube.com"
  },
  {
    "title": "LOL Caricatures- Adam Chua | Caricaturist.sg",
    "url": "https://www.youtube.com/watch?v=dKKA98SPY9w",
    "hostname": "www.youtube.com"
  },
  {
    "title": "Learn how I sketch and color in less than 7 minutes …",
    "url": "https://www.youtube.com/watch?v=FpInGL1Wxo0",
    "hostname": "www.youtube.com"
  },
  {
    "title": "World’s Fastest Caricaturist | Artist for your party: Alani J, Lehigh Valley!",
    "url": "https://www.youtube.com/watch?v=GxEswYLBqMI",
    "hostname": "www.youtube.com"
  },
  {
    "title": "2 en 1 La Hora del Dibujo•The Drawing Hour•Alani J Caricaturista Más Rápido del Mundo Worlds Fastest",
    "url": "https://www.youtube.com/watch?v=4MnoKwaA48A",
    "hostname": "www.youtube.com"
  },
  {
    "title": "Caricature Reveal Compilation PART 1, Reactions to Art by Alani J",
    "url": "https://www.youtube.com/watch?v=0PqTjCFWX-M",
    "hostname": "www.youtube.com"
  },
  {
    "title": "Un siglo de caricaturistas mexicanos en el metro Zapata",
    "url": "https://www.youtube.com/watch?v=i3HeDm153_M",
    "hostname": "www.youtube.com"
  },
  {
    "title": "Thomas Fluharty | The Gift of Art and the Joy of Creating | Guild Program",
    "url": "https://www.youtube.com/watch?v=0MekqNrab0E",
    "hostname": "www.youtube.com"
  },
  {
    "title": "Thomas Fluharty and the Unforgiving Prismacolor 901",
    "url": "https://www.youtube.com/watch?v=MGE36t7a6To",
    "hostname": "www.youtube.com"
  },
  {
    "title": "Charcoal Techniques with Thomas Fluharty",
    "url": "https://www.youtube.com/watch?v=75TIQCCr_ro",
    "hostname": "www.youtube.com"
  },
  {
    "title": "Thor speedpainting by Alex Gallego",
    "url": "https://www.youtube.com/watch?v=zAcBXPwkNqs",
    "hostname": "www.youtube.com"
  },
  {
    "title": "Alex Gallego's painting process: Penny (Kaley Cuoco) from Big Bang Theory",
    "url": "https://www.youtube.com/watch?v=LcMhc4p4TLE",
    "hostname": "www.youtube.com"
  },
  {
    "title": "Painting Leslie Nielsen",
    "url": "https://www.youtube.com/watch?v=9RR5HvsV7w0",
    "hostname": "www.youtube.com"
  },
  {
    "title": "Bruce Willis (John McLane) caricature painting by Alex Gallego",
    "url": "https://www.youtube.com/watch?v=ZlmV_ZNndVU",
    "hostname": "www.youtube.com"
  },
  {
    "title": "Jason Seiler portrait",
    "url": "https://www.youtube.com/watch?v=gXrOabRm07k",
    "hostname": "www.youtube.com"
  },
  {
    "title": "Jason Seiler - Digital Caricature Artist & illustrator - Caricature Reel",
    "url": "https://www.youtube.com/watch?v=T3wEDnqDJ8A",
    "hostname": "www.youtube.com"
  },
  {
    "title": "Painting Mark Ruffalo with Jason Seiler",
    "url": "https://www.youtube.com/watch?v=wQ0-ONwJPwQ",
    "hostname": "www.youtube.com"
  },
  {
    "title": "Jason Seiler Visiting Artist Lecture at the American Academy of Art",
    "url": "https://www.youtube.com/watch?v=1SMGEQNTUDc",
    "hostname": "www.youtube.com"
  },
  {
    "title": "Charley Belcher Interview Part 1 (ZOMG Paul McCartney ❤️)",
    "url": "https://www.youtube.com/watch?v=UBeR6LwYsPc",
    "hostname": "www.youtube.com"
  },
  {
    "title": "Charley Belcher Interview Part 2",
    "url": "https://www.youtube.com/watch?v=50Hl7C8ZSJA",
    "hostname": "www.youtube.com"
  },
  {
    "title": "Charley Belcher Interview Part 3",
    "url": "https://www.youtube.com/watch?v=Ms3oD0RTgzU",
    "hostname": "www.youtube.com"
  },
  {
    "title": "La Famiglia - Tribute to the Godfather by David O'Keefe",
    "url": "https://www.youtube.com/watch?v=Cku7ADZv9KE",
    "hostname": "www.youtube.com"
  },
  {
    "title": "David Painting in the St Armands Gallery",
    "url": "https://www.youtube.com/watch?v=6-KzdAAx9Pc",
    "hostname": "www.youtube.com"
  },
  {
    "title": "¿Cómo hacer una Caricatura Fisionómica? (Capitulo 01: Piloto)por KristoCaricaturas",
    "url": "https://www.youtube.com/watch?v=ToVIYojqPBQ",
    "hostname": "www.youtube.com"
  },
  {
    "title": "How to draw a Basic Caricature for Beginners",
    "url": "https://www.youtube.com/watch?v=KP-mx0tnbPg",
    "hostname": "www.youtube.com"
  },
  {
    "title": "Caricature Drawing 101",
    "url": "https://www.youtube.com/watch?v=crGNyjJQAc4",
    "hostname": "www.youtube.com"
  },
  {
    "title": "The Basics of Drawing a Caricature of a Female Face.",
    "url": "https://www.youtube.com/watch?v=4o-5CUVVdAU",
    "hostname": "www.youtube.com"
  },
  {
    "title": "How To Draw Caricature Eyes - Women's",
    "url": "https://www.youtube.com/watch?v=M3QkanEN4TM",
    "hostname": "www.youtube.com"
  },
  {
    "title": "How To Draw a Basic Easy Caricature",
    "url": "https://www.youtube.com/watch?v=bEzbCP9wtB0",
    "hostname": "www.youtube.com"
  },
  {
    "title": "6 Steps to Draw Anything",
    "url": "https://www.youtube.com/watch?v=6T_-DiAzYBc",
    "hostname": "www.youtube.com"
  },
  {
    "title": "Caricaturist John Kascht | Detroit Performs Clip",
    "url": "https://www.youtube.com/watch?v=5ZWe0XAkGmU",
    "hostname": "www.youtube.com"
  },
  {
    "title": "Michigan International Prep School Presents: Caricature Masterclass with Mark Berry",
    "url": "https://www.youtube.com/watch?v=28xOpGbpzqQ",
    "hostname": "www.youtube.com"
  },
  {
    "title": "Kim Jung Gi - How to Become a Master",
    "url": "https://www.youtube.com/watch?v=aoqu5SEFqRI",
    "hostname": "www.youtube.com"
  },
  {
    "title": "Drew: The Man Behind the Poster - Official Trailer (HD) Documentary",
    "url": "https://www.youtube.com/watch?v=vzXpdYTUTmo",
    "hostname": "www.youtube.com"
  },
  {
    "title": "Drew Struzan - Tracing ❤️❤️❤️❤️❤️❤️❤️",
    "url": "https://www.youtube.com/watch?v=0fEMJp70tGU",
    "hostname": "www.youtube.com"
  },
  {
    "title": "Best ever Jack Nicholson and Joe Pesci impression by Jim Breuer",
    "url": "https://www.youtube.com/watch?v=HP6XK9WMBy4",
    "hostname": "www.youtube.com"
  }
]