[
  {
    "title": "How Amelia Earhart Did It",
    "url": "https://www.youtube.com/watch?v=zv1Gqmio7Zg",
    "hostname": "www.youtube.com"
  },
  {
    "title": "Amelia Earhart: Queen Of The Air",
    "url": "https://www.youtube.com/watch?v=k6LsxtFOYFA",
    "hostname": "www.youtube.com"
  },
  {
    "title": "Underwater Discovery and Adventure: The Story of Jacques Cousteau",
    "url": "https://www.youtube.com/watch?v=9z08SD5iRuk",
    "hostname": "www.youtube.com"
  },
  {
    "title": "World Without Sun von Jaques Cousteau",
    "url": "https://www.youtube.com/watch?v=4mp0PA-O_4c",
    "hostname": "www.youtube.com"
  },
  {
    "title": "Shackleton's Voyage of Endurance",
    "url": "https://www.youtube.com/watch?v=HuKUX-7x2Ws",
    "hostname": "www.youtube.com"
  },
  {
    "title": "Retracing Ernest Shackleton's Doomed Expedition To Cross The Antarctic",
    "url": "https://www.youtube.com/watch?v=1jFP7t8JZT8",
    "hostname": "www.youtube.com"
  },
  {
    "title": "Edmund Hillary and Tenzing Norgay climb Everest - 1953 archive video",
    "url": "https://www.youtube.com/watch?v=X4egTHmDYho",
    "hostname": "www.youtube.com"
  },
  {
    "title": "Sir Edmund Hillary Interviewed by Wade Davis",
    "url": "https://www.youtube.com/watch?v=2e58ZJm7GLg",
    "hostname": "www.youtube.com"
  },
  {
    "title": "Learn to travel -- travel to learn: Robin Esrock at TEDxVancouver",
    "url": "https://www.youtube.com/watch?v=S0TemlxiMdw",
    "hostname": "www.youtube.com"
  },
  {
    "title": "How to travel the world with almost no money by Tomislav Perko",
    "url": "https://www.youtube.com/watch?v=R7vmHGAshi8",
    "hostname": "www.youtube.com"
  },
  {
    "title": "Travel More & Buy Less. by Luis Vargas",
    "url": "https://www.youtube.com/watch?v=AlCqyZEXM1I",
    "hostname": "www.youtube.com"
  },
  {
    "title": "The value of travel by Rick Steves",
    "url": "https://www.youtube.com/watch?v=kYXiegTXsEs",
    "hostname": "www.youtube.com"
  },
  {
    "title": "How adventure makes you smarter, stronger, and attractive by Tyler Tervooren",
    "url": "https://www.youtube.com/watch?v=2S7Iz38ZDik",
    "hostname": "www.youtube.com"
  },
  {
    "title": "I'm home: How 10 years of travel helped me find belonging by Phil Cha",
    "url": "https://www.youtube.com/watch?v=bXBgitBX5Q0",
    "hostname": "www.youtube.com"
  },
  {
    "title": "Say 'yes' to your adventure: Matthew Trinetti",
    "url": "https://www.youtube.com/watch?v=H9gh1FpoZqI",
    "hostname": "www.youtube.com"
  },
  {
    "title": "Live Life to the fullest by Nick Martin",
    "url": "https://www.youtube.com/watch?v=zO--hYecQKo",
    "hostname": "www.youtube.com"
  },
  {
    "title": "Barèges, the steep one",
    "url": "https://www.youtube.com/watch?v=Tm7l11PGldI",
    "hostname": "www.youtube.com"
  },
  {
    "title": "What It Takes to Be an Adventurer",
    "url": "https://www.youtube.com/watch?v=aoq6jNBtNtw",
    "hostname": "www.youtube.com"
  },
  {
    "title": "What It Means To Be An Adventure Photographer",
    "url": "https://www.youtube.com/watch?v=Gdnc0hUfpec",
    "hostname": "www.youtube.com"
  },
  {
    "title": "Welcome to an Adventurer’s Year-Round Paradise: British Columbia",
    "url": "https://www.youtube.com/watch?v=2cleBlYbla8",
    "hostname": "www.youtube.com"
  },
  {
    "title": "My Life As an Adventure Photographer",
    "url": "https://www.youtube.com/watch?v=MYECOURXy5M",
    "hostname": "www.youtube.com"
  },
  {
    "title": "A Quest to Find Canada’s Elusive Coastal Wolf",
    "url": "https://www.youtube.com/watch?v=duYDQPEzmvQ",
    "hostname": "www.youtube.com"
  },
  {
    "title": "My Life As an Adventure Filmmaker and Photographer (Part 1)",
    "url": "https://www.youtube.com/watch?v=5j5TdORzgh0",
    "hostname": "www.youtube.com"
  },
  {
    "title": "My Life As an Adventure Filmmaker and Photographer (Part 2)",
    "url": "https://www.youtube.com/watch?v=NtI7MsPIf-Y",
    "hostname": "www.youtube.com"
  },
  {
    "title": "After the Avalanche: Life as an Adventure Photographer With PTSD (Part 1)",
    "url": "https://www.youtube.com/watch?v=pO2XEcpJROU",
    "hostname": "www.youtube.com"
  },
  {
    "title": "After the Avalanche: Life as an Adventure Photographer With PTSD (Part 2)",
    "url": "https://www.youtube.com/watch?v=hn_cOO80sHM",
    "hostname": "www.youtube.com"
  },
  {
    "title": "Hardangervidda expedition, Norway #1",
    "url": "https://www.youtube.com/watch?v=PL3sEcMYyQ0",
    "hostname": "www.youtube.com"
  },
  {
    "title": "Arctic Pulk Expedition - crossing the Finnmark Plateau, Norway",
    "url": "https://www.youtube.com/watch?v=zKkJlTUJyOM",
    "hostname": "www.youtube.com"
  },
  {
    "title": "This Explorer Has Seen More Of The World Than Anyone Currently Alive",
    "url": "https://www.youtube.com/watch?v=z6ZE4v1tV9A",
    "hostname": "www.youtube.com"
  },
  {
    "title": "Explorer Mike Horn Speaks at EOS Global Hackathon Grand Finale",
    "url": "https://www.youtube.com/watch?v=AWtcmJ_VXpE",
    "hostname": "www.youtube.com"
  },
  {
    "title": "TEDxPearlRiver - Mike Horn - Pangea: Exploring the Limits",
    "url": "https://www.youtube.com/watch?v=4yFOYGCm2Yk",
    "hostname": "www.youtube.com"
  },
  {
    "title": "Journey to the Deep with James Cameron - Nierenberg Prize 2013",
    "url": "https://www.youtube.com/watch?v=f4SlMxTRhPM",
    "hostname": "www.youtube.com"
  },
  {
    "title": "Titanic: The Final Word With James Cameron - Full Documentary in HD",
    "url": "https://www.youtube.com/watch?v=d-5MXNz7XKQ",
    "hostname": "www.youtube.com"
  },
  {
    "title": "The Lost Forest | Nobel Peace Prize Shorts",
    "url": "https://www.youtube.com/watch?v=aDoanNM7O_s",
    "hostname": "www.youtube.com"
  },
  {
    "title": "Meet the 2013 Adventurers of the Year",
    "url": "https://www.youtube.com/watch?v=eY03CObhqwE",
    "hostname": "www.youtube.com"
  },
  {
    "title": "My life as a professional adventurer by Chuck Berry",
    "url": "https://www.youtube.com/watch?v=H2Z7H8tFd9Q",
    "hostname": "www.youtube.com"
  },
  {
    "title": "YouTube Channel",
    "url": "https://www.youtube.com/user/jugglerguy1",
    "hostname": "www.youtube.com"
  },
  {
    "title": "Rock Hunting the Beach at Rockport State Park",
    "url": "https://www.youtube.com/watch?v=XRJBk3Ue7uY",
    "hostname": "www.youtube.com"
  },
  {
    "title": "YouTube Channel",
    "url": "https://www.youtube.com/channel/UC9D3lVCpT6kljc61gm6h_Yg",
    "hostname": "www.youtube.com"
  },
  {
    "title": "Metal Detecting for Coins",
    "url": "https://www.youtube.com/watch?v=npixJs1UcUo",
    "hostname": "www.youtube.com"
  },
  {
    "title": "YouTube Channel",
    "url": "https://www.youtube.com/user/driftwoodnic",
    "hostname": "www.youtube.com"
  },
  {
    "title": "Mudlarking The River Thames - THREE mystery finds",
    "url": "https://www.youtube.com/watch?v=Byhsobb6S2A",
    "hostname": "www.youtube.com"
  },
  {
    "title": "YouTube Channel",
    "url": "https://www.youtube.com/channel/UCv61IAZLDELwk2Kk5hfX0mg",
    "hostname": "www.youtube.com"
  },
  {
    "title": "OMG! I Found A Huge Silver Treasure Hoard Metal Detecting!",
    "url": "https://www.youtube.com/watch?v=JDC3SUK3axM",
    "hostname": "www.youtube.com"
  },
  {
    "title": "YouTube Channel",
    "url": "https://www.youtube.com/channel/UCWaFLqinCCMRgnIyF_CuoaQ",
    "hostname": "www.youtube.com"
  },
  {
    "title": "Forgotten bunker found and opened",
    "url": "https://www.youtube.com/watch?v=KDPnWgVGuhc",
    "hostname": "www.youtube.com"
  },
  {
    "title": "Reuniting my Grandfather with his old motorcycle after 60 years apart!",
    "url": "https://www.youtube.com/watch?v=BqeBWukNAAQ",
    "hostname": "www.youtube.com"
  },
  {
    "title": "Helge Pedersen - 10 Years on 2 Wheels (1998)",
    "url": "https://www.youtube.com/watch?v=pvNwK5XZW48",
    "hostname": "www.youtube.com"
  },
  {
    "title": "La Ruta del Che - South American Motorbike Expedition",
    "url": "https://www.youtube.com/watch?v=zogsTjWXpwA",
    "hostname": "www.youtube.com"
  },
  {
    "title": "Motorcycle to South America",
    "url": "https://www.youtube.com/watch?v=oJ7F3f7YJbs",
    "hostname": "www.youtube.com"
  },
  {
    "title": "Up&Down Central Asia Adventure - Russia, Mongolia, Kyrgyzstan, Tajikistan, Uzbekistan",
    "url": "https://www.youtube.com/watch?v=fmmXvoKGNGk",
    "hostname": "www.youtube.com"
  },
  {
    "title": "GlobeRiders - Iceland Expedition (2001)",
    "url": "https://www.youtube.com/watch?v=dvokc2t7yGo",
    "hostname": "www.youtube.com"
  },
  {
    "title": "GlobeRiders - Eurasian Odyssey (2002)",
    "url": "https://www.youtube.com/watch?v=QoQjPq3YqJw",
    "hostname": "www.youtube.com"
  },
  {
    "title": "Through the Darién Gap with Helge Pedersen",
    "url": "https://www.youtube.com/watch?v=1FcPdJTviVA",
    "hostname": "www.youtube.com"
  },
  {
    "title": "Mini Bike Hammock Camping in a Canyon",
    "url": "https://www.youtube.com/watch?v=JweFDrQG1s0",
    "hostname": "www.youtube.com"
  },
  {
    "title": "Bike Road Trip",
    "url": "https://www.youtube.com/watch?v=X-WgGh9lvx4",
    "hostname": "www.youtube.com"
  },
  {
    "title": "Most Memorable Events in 60.000 kilometers of Motorcycling the World",
    "url": "https://www.youtube.com/watch?v=r6Dpwc1y3ZU",
    "hostname": "www.youtube.com"
  },
  {
    "title": "Season 1, Episode 1, KICKOFF!!",
    "url": "https://www.youtube.com/watch?v=l3lLNVQJFPA",
    "hostname": "www.youtube.com"
  },
  {
    "title": "YouTube Channel",
    "url": "https://www.youtube.com/channel/UCEIs9nkveW9WmYtsOcJBwTg",
    "hostname": "www.youtube.com"
  },
  {
    "title": "Adventures with Basanti",
    "url": "https://www.youtube.com/watch?v=l3lLNVQJFPA&list=PL8M9dV_BySaUE-uJADRFRrL6BiVpKC3-e",
    "hostname": "www.youtube.com"
  }
]