{
  "name": "westland-warrior-the-phreak",
  "id": "westland-warrior-the-phreak",
  "guid": "1c872779-a2eb-4c76-a333-56ade6ccfb4a",
  "title": "The Phreak",
  "date": "2022-09-25T19:00:27.601Z",
  "image": "warrior-the-phreak-cover.jpg",
  "artwork": null,
  "audio": null,
  "md": "Steve Jobs Interview about the Blue Box Story\n---------------------------------------------\n\n[![](/image/yid-HFURM8O-oYI.jpg)](https://www.youtube.com/watch?v=HFURM8O-oYI&t=13)\n\nBlue Box | Homemade Replica Blue Box For Phone Phreaking\n--------------------------------------------------------\n\n[![](/image/yid-CRp8XvwNSD0.jpg)](https://www.youtube.com/watch?v=CRp8XvwNSD0)\n\n20th Anniversary Redbox Radioshack tone dialer EC-389 Catalog no 65-721\n-----------------------------------------------------------------------\n\n[![](/image/yid-JAj0BMIODWo.jpg)](https://www.youtube.com/watch?v=JAj0BMIODWo)\n\nOldschool Radioshack Redbox pocket tone dialer\n----------------------------------------------\n\n[![](/image/yid-AXZMgHKhefk.jpg)](https://www.youtube.com/watch?v=AXZMgHKhefk)\n\nEmmanuel Goldstein, sock puppet Q&A\n-----------------------------------\n\n[![](/image/yid-AJir12xkUY4.jpg)](https://www.youtube.com/watch?v=AJir12xkUY4)\n\nPhiber Optik - Last Interview Before 1 Year In Prison (1993)\n------------------------------------------------------------\n\n[![](/image/yid-hkQ0BOrFTJk.jpg)](https://www.youtube.com/watch?v=hkQ0BOrFTJk)\n\nJoybubbles ❤️\n-------------\n\n[![](/image/yid-vVZm7I1CTBs.jpg)](https://www.youtube.com/watch?v=vVZm7I1CTBs)\n\nCovid Crops Prank Call\n----------------------\n\n[![](/image/yid-jG1T34uE58o.jpg)](https://www.youtube.com/watch?v=jG1T34uE58o)\n\nHarassing Black Friday Wal-Mart Customers with Prank Calls\n----------------------------------------------------------\n\n[![](/image/yid-RGmdwiz9zDE.jpg)](https://www.youtube.com/watch?v=RGmdwiz9zDE)\n\nThe Last HOPE (2008) - The Art of Social Engineering\n----------------------------------------------------\n\n[![](/image/yid-1M9pwYQSbQU.jpg)](https://www.youtube.com/watch?v=1M9pwYQSbQU)\n\nPhone Phreak Captain Crunch Rare Interview from '78\n---------------------------------------------------\n\n[![](/image/yid-n6TjjE8NHV0.jpg)](https://www.youtube.com/watch?v=n6TjjE8NHV0)\n\n2600 Interview with Kevin Mitnick\n---------------------------------\n\n[![](/image/yid-6OJyaML7_rw.jpg)](https://www.youtube.com/watch?v=6OJyaML7_rw)\n\nL0pht Heavy Industries\n----------------------\n\n[![](/image/yid-VVJldn_MmMY.jpg)](https://www.youtube.com/watch?v=VVJldn_MmMY)\n\nAmazon gave Ring video to police without user’s permission (FOR ANY PURPOSE!)\n-----------------------------------------------------------------------------\n\n[![](/image/yid-utPRvqhXfoo.jpg)](https://www.youtube.com/watch?v=utPRvqhXfoo)\n\n48 Dirty Little Secrets Cryptographers Don’t Want You To Know\n-------------------------------------------------------------\n\n[![](/image/yid-iZa_XKpj9X4.jpg)](https://www.youtube.com/watch?v=iZa_XKpj9X4)\n\nBroadpwn: Remotely Compromising Android and iOS via a Bug in Broadcom's Wi-Fi Chipsets\n--------------------------------------------------------------------------------------\n\n[![](/image/yid-TDk2RId8LFo.jpg)](https://www.youtube.com/watch?v=TDk2RId8LFo)\n\nPolice are tracking you and your license plates\n-----------------------------------------------\n\n[![](/image/yid-DH7edXaZS0A.jpg)](https://www.youtube.com/watch?v=DH7edXaZS0A)\n\nThe Stingray: How Law Enforcement Can Track Your Every Move\n-----------------------------------------------------------\n\n[![](/image/yid-wzSgLpNrr2E.jpg)](https://www.youtube.com/watch?v=wzSgLpNrr2E)\n\nWhat Are My Rights With Police? (When I Get Pulled Over)\n--------------------------------------------------------\n\n[![](/image/yid-f26QJKREYB8.jpg)](https://www.youtube.com/watch?v=f26QJKREYB8&t=44)\n\nMichigan Police Sergeant Doesn't Know The Law\n---------------------------------------------\n\n[![](/image/yid-6wsDmZo9UMI.jpg)](https://www.youtube.com/watch?v=6wsDmZo9UMI)\n\nDon't Talk to the Police\n------------------------\n\n[![](/image/yid-d-7o9xYp7eE.jpg)](https://www.youtube.com/watch?v=d-7o9xYp7eE)\n\nHow to make a simple $7 IMSI Catcher\n------------------------------------\n\n[![](/image/yid-UjwgNd_as30.jpg)](https://www.youtube.com/watch?v=UjwgNd_as30)\n\nCatching IMSI Catchers\n----------------------\n\n[![](/image/yid-eivHO1OzF5E.jpg)](https://www.youtube.com/watch?v=eivHO1OzF5E)\n\nProject Overwatch: Multinational Effort to Combat IMSI Catchers (Intercept SMS And Track Location For $7)\n---------------------------------------------------------------------------------------------------------\n\n[![](/image/yid-UG5juhuhE2g.jpg)](https://www.youtube.com/watch?v=UG5juhuhE2g)\n\nBSIDES CPT 2019 - Hacking satellites with Software Defined Radio (SDR) - Gerard de Jong\n---------------------------------------------------------------------------------------\n\n[![](/image/yid-gMwciWchH3Q.jpg)](https://www.youtube.com/watch?v=gMwciWchH3Q)\n\nThe Coolest Radio You've Probably Never Heard Of\n------------------------------------------------\n\n[![](/image/yid-h4x7cGALaC8.jpg)](https://www.youtube.com/watch?v=h4x7cGALaC8&t=61)\n\nLocating Cellular Signal with HackRF Spectrum Analyzer SDR Software\n-------------------------------------------------------------------\n\n[![](/image/yid-aFHWAEb3sn4.jpg)](https://www.youtube.com/watch?v=aFHWAEb3sn4)\n\nHow Telephone Phreaking Worked (Starts at 4:30)\n-----------------------------------------------\n\n[![](/image/yid-4tHyZdtXULw.jpg)](https://www.youtube.com/watch?v=4tHyZdtXULw)\n\nHackers The History Of Hacking - Phone Phreaking, Cap.Crunch, Wozniak, Mitnick\n------------------------------------------------------------------------------\n\n[![](/image/yid-FufYSx2_6Bg.jpg)](https://www.youtube.com/watch?v=FufYSx2_6Bg)\n\nDutch Hacker Attacking Pentagon via FTP (1991)\n----------------------------------------------\n\n[![](/image/yid-3ZU2DHcjrcI.jpg)](https://www.youtube.com/watch?v=3ZU2DHcjrcI)\n\nThe Jerky Boys - Piano Tuner\n----------------------------\n\n[![](/image/yid-eajkTddpeQQ.jpg)](https://www.youtube.com/watch?v=eajkTddpeQQ)\n\nJerky Boys - Sol Rosenberg's Glasses\n------------------------------------\n\n[![](/image/yid-jF0ajgT_09s.jpg)](https://www.youtube.com/watch?v=jF0ajgT_09s)\n\nThe Jerky Boys - Drinking Problem\n---------------------------------\n\n[![](/image/yid-ZllDjMXSjOE.jpg)](https://www.youtube.com/watch?v=ZllDjMXSjOE)\n\nCact-Eye Hidden Camera Prank Calls\n----------------------------------\n\n[![](/image/yid-p1kWQOa-ULM.jpg)](https://www.youtube.com/watch?v=p1kWQOa-ULM)\n\nRadio and Swap Shop Prank Calls\n-------------------------------\n\n[![](/image/yid-kHA79JHGlOk.jpg)](https://www.youtube.com/watch?v=kHA79JHGlOk)\n\nTour of the Cacti Radio Studio\n------------------------------\n\n[![](/image/yid-Q1YBk6tbM8s.jpg)](https://www.youtube.com/watch?v=Q1YBk6tbM8s)\n\nPump Up The Volume\n------------------\n\n[![](/image/yid-uo-km-qfJe8.jpg)](https://www.youtube.com/watch?v=uo-km-qfJe8)\n\nClassroom Craziness Compilation\n-------------------------------\n\n[![](/image/yid-lwEFEIxcj4Q.jpg)](https://www.youtube.com/watch?v=lwEFEIxcj4Q)\n\n\\*Trance\\* Orbital - Halcyon and On and On ( Hackers / 1995 )\n-------------------------------------------------------------\n\n[![](/image/yid-33WuGp6fs3s.jpg)](https://www.youtube.com/watch?v=33WuGp6fs3s)\n\nThe Conscience of a Hacker\n--------------------------\n\n[![](/image/yid-0tEnnvZbYek.jpg)](https://www.youtube.com/watch?v=0tEnnvZbYek)",
  "html": "<div class=\"section yt\">\n  <header>\n    <h2>Steve Jobs Interview about the Blue Box Story</h2>\n  </header>\n  <figure>\n    <a href=\"https://www.youtube.com/watch?v=HFURM8O-oYI&t=13\" class=\"no-tufte-underline\" title=\"Steve Jobs Interview about the Blue Box Story\">\n      <img src=\"/image/yid-HFURM8O-oYI.jpg\" alt=\"Steve Jobs Interview about the Blue Box Story\">\n    </a>\n    <figcaption>Steve Jobs Interview about the Blue Box Story</figcaption>\n  </figure>\n  <p><a href=\"https://www.youtube.com/watch?v=HFURM8O-oYI&t=13\" title=\"Steve Jobs Interview about the Blue Box Story\">Play Video</a></p>\n</div>\n<div class=\"section yt\">\n  <header>\n    <h2>Blue Box | Homemade Replica Blue Box For Phone Phreaking</h2>\n  </header>\n  <figure>\n    <a href=\"https://www.youtube.com/watch?v=CRp8XvwNSD0\" class=\"no-tufte-underline\" title=\"Blue Box | Homemade Replica Blue Box For Phone Phreaking\">\n      <img src=\"/image/yid-CRp8XvwNSD0.jpg\" alt=\"Blue Box | Homemade Replica Blue Box For Phone Phreaking\">\n    </a>\n    <figcaption>Blue Box | Homemade Replica Blue Box For Phone Phreaking</figcaption>\n  </figure>\n  <p><a href=\"https://www.youtube.com/watch?v=CRp8XvwNSD0\" title=\"Blue Box | Homemade Replica Blue Box For Phone Phreaking\">Play Video</a></p>\n</div>\n<div class=\"section yt\">\n  <header>\n    <h2>20th Anniversary Redbox Radioshack tone dialer EC-389 Catalog no 65-721</h2>\n  </header>\n  <figure>\n    <a href=\"https://www.youtube.com/watch?v=JAj0BMIODWo\" class=\"no-tufte-underline\" title=\"20th Anniversary Redbox Radioshack tone dialer EC-389 Catalog no 65-721\">\n      <img src=\"/image/yid-JAj0BMIODWo.jpg\" alt=\"20th Anniversary Redbox Radioshack tone dialer EC-389 Catalog no 65-721\">\n    </a>\n    <figcaption>20th Anniversary Redbox Radioshack tone dialer EC-389 Catalog no 65-721</figcaption>\n  </figure>\n  <p><a href=\"https://www.youtube.com/watch?v=JAj0BMIODWo\" title=\"20th Anniversary Redbox Radioshack tone dialer EC-389 Catalog no 65-721\">Play Video</a></p>\n</div>\n<div class=\"section yt\">\n  <header>\n    <h2>Oldschool Radioshack Redbox pocket tone dialer</h2>\n  </header>\n  <figure>\n    <a href=\"https://www.youtube.com/watch?v=AXZMgHKhefk\" class=\"no-tufte-underline\" title=\"Oldschool Radioshack Redbox pocket tone dialer\">\n      <img src=\"/image/yid-AXZMgHKhefk.jpg\" alt=\"Oldschool Radioshack Redbox pocket tone dialer\">\n    </a>\n    <figcaption>Oldschool Radioshack Redbox pocket tone dialer</figcaption>\n  </figure>\n  <p><a href=\"https://www.youtube.com/watch?v=AXZMgHKhefk\" title=\"Oldschool Radioshack Redbox pocket tone dialer\">Play Video</a></p>\n</div>\n<div class=\"section yt\">\n  <header>\n    <h2>Emmanuel Goldstein, sock puppet Q&amp;A</h2>\n  </header>\n  <figure>\n    <a href=\"https://www.youtube.com/watch?v=AJir12xkUY4\" class=\"no-tufte-underline\" title=\"Emmanuel Goldstein, sock puppet Q&amp;A\">\n      <img src=\"/image/yid-AJir12xkUY4.jpg\" alt=\"Emmanuel Goldstein, sock puppet Q&amp;A\">\n    </a>\n    <figcaption>Emmanuel Goldstein, sock puppet Q&amp;A</figcaption>\n  </figure>\n  <p><a href=\"https://www.youtube.com/watch?v=AJir12xkUY4\" title=\"Emmanuel Goldstein, sock puppet Q&amp;A\">Play Video</a></p>\n</div>\n<div class=\"section yt\">\n  <header>\n    <h2>Phiber Optik - Last Interview Before 1 Year In Prison (1993)</h2>\n  </header>\n  <figure>\n    <a href=\"https://www.youtube.com/watch?v=hkQ0BOrFTJk\" class=\"no-tufte-underline\" title=\"Phiber Optik - Last Interview Before 1 Year In Prison (1993)\">\n      <img src=\"/image/yid-hkQ0BOrFTJk.jpg\" alt=\"Phiber Optik - Last Interview Before 1 Year In Prison (1993)\">\n    </a>\n    <figcaption>Phiber Optik - Last Interview Before 1 Year In Prison (1993)</figcaption>\n  </figure>\n  <p><a href=\"https://www.youtube.com/watch?v=hkQ0BOrFTJk\" title=\"Phiber Optik - Last Interview Before 1 Year In Prison (1993)\">Play Video</a></p>\n</div>\n<div class=\"section yt\">\n  <header>\n    <h2>Joybubbles ❤️</h2>\n  </header>\n  <figure>\n    <a href=\"https://www.youtube.com/watch?v=vVZm7I1CTBs\" class=\"no-tufte-underline\" title=\"Joybubbles ❤️\">\n      <img src=\"/image/yid-vVZm7I1CTBs.jpg\" alt=\"Joybubbles ❤️\">\n    </a>\n    <figcaption>Joybubbles ❤️</figcaption>\n  </figure>\n  <p><a href=\"https://www.youtube.com/watch?v=vVZm7I1CTBs\" title=\"Joybubbles ❤️\">Play Video</a></p>\n</div>\n<div class=\"section yt\">\n  <header>\n    <h2>Covid Crops Prank Call</h2>\n  </header>\n  <figure>\n    <a href=\"https://www.youtube.com/watch?v=jG1T34uE58o\" class=\"no-tufte-underline\" title=\"Covid Crops Prank Call\">\n      <img src=\"/image/yid-jG1T34uE58o.jpg\" alt=\"Covid Crops Prank Call\">\n    </a>\n    <figcaption>Covid Crops Prank Call</figcaption>\n  </figure>\n  <p><a href=\"https://www.youtube.com/watch?v=jG1T34uE58o\" title=\"Covid Crops Prank Call\">Play Video</a></p>\n</div>\n<div class=\"section yt\">\n  <header>\n    <h2>Harassing Black Friday Wal-Mart Customers with Prank Calls</h2>\n  </header>\n  <figure>\n    <a href=\"https://www.youtube.com/watch?v=RGmdwiz9zDE\" class=\"no-tufte-underline\" title=\"Harassing Black Friday Wal-Mart Customers with Prank Calls\">\n      <img src=\"/image/yid-RGmdwiz9zDE.jpg\" alt=\"Harassing Black Friday Wal-Mart Customers with Prank Calls\">\n    </a>\n    <figcaption>Harassing Black Friday Wal-Mart Customers with Prank Calls</figcaption>\n  </figure>\n  <p><a href=\"https://www.youtube.com/watch?v=RGmdwiz9zDE\" title=\"Harassing Black Friday Wal-Mart Customers with Prank Calls\">Play Video</a></p>\n</div>\n<div class=\"section yt\">\n  <header>\n    <h2>The Last HOPE (2008) - The Art of Social Engineering</h2>\n  </header>\n  <figure>\n    <a href=\"https://www.youtube.com/watch?v=1M9pwYQSbQU\" class=\"no-tufte-underline\" title=\"The Last HOPE (2008) - The Art of Social Engineering\">\n      <img src=\"/image/yid-1M9pwYQSbQU.jpg\" alt=\"The Last HOPE (2008) - The Art of Social Engineering\">\n    </a>\n    <figcaption>The Last HOPE (2008) - The Art of Social Engineering</figcaption>\n  </figure>\n  <p><a href=\"https://www.youtube.com/watch?v=1M9pwYQSbQU\" title=\"The Last HOPE (2008) - The Art of Social Engineering\">Play Video</a></p>\n</div>\n<div class=\"section yt\">\n  <header>\n    <h2>Phone Phreak Captain Crunch Rare Interview from &#x27;78</h2>\n  </header>\n  <figure>\n    <a href=\"https://www.youtube.com/watch?v=n6TjjE8NHV0\" class=\"no-tufte-underline\" title=\"Phone Phreak Captain Crunch Rare Interview from &#x27;78\">\n      <img src=\"/image/yid-n6TjjE8NHV0.jpg\" alt=\"Phone Phreak Captain Crunch Rare Interview from &#x27;78\">\n    </a>\n    <figcaption>Phone Phreak Captain Crunch Rare Interview from &#x27;78</figcaption>\n  </figure>\n  <p><a href=\"https://www.youtube.com/watch?v=n6TjjE8NHV0\" title=\"Phone Phreak Captain Crunch Rare Interview from &#x27;78\">Play Video</a></p>\n</div>\n<div class=\"section yt\">\n  <header>\n    <h2>2600 Interview with Kevin Mitnick</h2>\n  </header>\n  <figure>\n    <a href=\"https://www.youtube.com/watch?v=6OJyaML7_rw\" class=\"no-tufte-underline\" title=\"2600 Interview with Kevin Mitnick\">\n      <img src=\"/image/yid-6OJyaML7_rw.jpg\" alt=\"2600 Interview with Kevin Mitnick\">\n    </a>\n    <figcaption>2600 Interview with Kevin Mitnick</figcaption>\n  </figure>\n  <p><a href=\"https://www.youtube.com/watch?v=6OJyaML7_rw\" title=\"2600 Interview with Kevin Mitnick\">Play Video</a></p>\n</div>\n<div class=\"section yt\">\n  <header>\n    <h2>L0pht Heavy Industries</h2>\n  </header>\n  <figure>\n    <a href=\"https://www.youtube.com/watch?v=VVJldn_MmMY\" class=\"no-tufte-underline\" title=\"L0pht Heavy Industries\">\n      <img src=\"/image/yid-VVJldn_MmMY.jpg\" alt=\"L0pht Heavy Industries\">\n    </a>\n    <figcaption>L0pht Heavy Industries</figcaption>\n  </figure>\n  <p><a href=\"https://www.youtube.com/watch?v=VVJldn_MmMY\" title=\"L0pht Heavy Industries\">Play Video</a></p>\n</div>\n<div class=\"section yt\">\n  <header>\n    <h2>Amazon gave Ring video to police without user’s permission (FOR ANY PURPOSE!)</h2>\n  </header>\n  <figure>\n    <a href=\"https://www.youtube.com/watch?v=utPRvqhXfoo\" class=\"no-tufte-underline\" title=\"Amazon gave Ring video to police without user’s permission (FOR ANY PURPOSE!)\">\n      <img src=\"/image/yid-utPRvqhXfoo.jpg\" alt=\"Amazon gave Ring video to police without user’s permission (FOR ANY PURPOSE!)\">\n    </a>\n    <figcaption>Amazon gave Ring video to police without user’s permission (FOR ANY PURPOSE!)</figcaption>\n  </figure>\n  <p><a href=\"https://www.youtube.com/watch?v=utPRvqhXfoo\" title=\"Amazon gave Ring video to police without user’s permission (FOR ANY PURPOSE!)\">Play Video</a></p>\n</div>\n<div class=\"section yt\">\n  <header>\n    <h2>48 Dirty Little Secrets Cryptographers Don’t Want You To Know</h2>\n  </header>\n  <figure>\n    <a href=\"https://www.youtube.com/watch?v=iZa_XKpj9X4\" class=\"no-tufte-underline\" title=\"48 Dirty Little Secrets Cryptographers Don’t Want You To Know\">\n      <img src=\"/image/yid-iZa_XKpj9X4.jpg\" alt=\"48 Dirty Little Secrets Cryptographers Don’t Want You To Know\">\n    </a>\n    <figcaption>48 Dirty Little Secrets Cryptographers Don’t Want You To Know</figcaption>\n  </figure>\n  <p><a href=\"https://www.youtube.com/watch?v=iZa_XKpj9X4\" title=\"48 Dirty Little Secrets Cryptographers Don’t Want You To Know\">Play Video</a></p>\n</div>\n<div class=\"section yt\">\n  <header>\n    <h2>Broadpwn: Remotely Compromising Android and iOS via a Bug in Broadcom&#x27;s Wi-Fi Chipsets</h2>\n  </header>\n  <figure>\n    <a href=\"https://www.youtube.com/watch?v=TDk2RId8LFo\" class=\"no-tufte-underline\" title=\"Broadpwn: Remotely Compromising Android and iOS via a Bug in Broadcom&#x27;s Wi-Fi Chipsets\">\n      <img src=\"/image/yid-TDk2RId8LFo.jpg\" alt=\"Broadpwn: Remotely Compromising Android and iOS via a Bug in Broadcom&#x27;s Wi-Fi Chipsets\">\n    </a>\n    <figcaption>Broadpwn: Remotely Compromising Android and iOS via a Bug in Broadcom&#x27;s Wi-Fi Chipsets</figcaption>\n  </figure>\n  <p><a href=\"https://www.youtube.com/watch?v=TDk2RId8LFo\" title=\"Broadpwn: Remotely Compromising Android and iOS via a Bug in Broadcom&#x27;s Wi-Fi Chipsets\">Play Video</a></p>\n</div>\n<div class=\"section yt\">\n  <header>\n    <h2>Police are tracking you and your license plates</h2>\n  </header>\n  <figure>\n    <a href=\"https://www.youtube.com/watch?v=DH7edXaZS0A\" class=\"no-tufte-underline\" title=\"Police are tracking you and your license plates\">\n      <img src=\"/image/yid-DH7edXaZS0A.jpg\" alt=\"Police are tracking you and your license plates\">\n    </a>\n    <figcaption>Police are tracking you and your license plates</figcaption>\n  </figure>\n  <p><a href=\"https://www.youtube.com/watch?v=DH7edXaZS0A\" title=\"Police are tracking you and your license plates\">Play Video</a></p>\n</div>\n<div class=\"section yt\">\n  <header>\n    <h2>The Stingray: How Law Enforcement Can Track Your Every Move</h2>\n  </header>\n  <figure>\n    <a href=\"https://www.youtube.com/watch?v=wzSgLpNrr2E\" class=\"no-tufte-underline\" title=\"The Stingray: How Law Enforcement Can Track Your Every Move\">\n      <img src=\"/image/yid-wzSgLpNrr2E.jpg\" alt=\"The Stingray: How Law Enforcement Can Track Your Every Move\">\n    </a>\n    <figcaption>The Stingray: How Law Enforcement Can Track Your Every Move</figcaption>\n  </figure>\n  <p><a href=\"https://www.youtube.com/watch?v=wzSgLpNrr2E\" title=\"The Stingray: How Law Enforcement Can Track Your Every Move\">Play Video</a></p>\n</div>\n<div class=\"section yt\">\n  <header>\n    <h2>What Are My Rights With Police? (When I Get Pulled Over)</h2>\n  </header>\n  <figure>\n    <a href=\"https://www.youtube.com/watch?v=f26QJKREYB8&t=44\" class=\"no-tufte-underline\" title=\"What Are My Rights With Police? (When I Get Pulled Over)\">\n      <img src=\"/image/yid-f26QJKREYB8.jpg\" alt=\"What Are My Rights With Police? (When I Get Pulled Over)\">\n    </a>\n    <figcaption>What Are My Rights With Police? (When I Get Pulled Over)</figcaption>\n  </figure>\n  <p><a href=\"https://www.youtube.com/watch?v=f26QJKREYB8&t=44\" title=\"What Are My Rights With Police? (When I Get Pulled Over)\">Play Video</a></p>\n</div>\n<div class=\"section yt\">\n  <header>\n    <h2>Michigan Police Sergeant Doesn&#x27;t Know The Law</h2>\n  </header>\n  <figure>\n    <a href=\"https://www.youtube.com/watch?v=6wsDmZo9UMI\" class=\"no-tufte-underline\" title=\"Michigan Police Sergeant Doesn&#x27;t Know The Law\">\n      <img src=\"/image/yid-6wsDmZo9UMI.jpg\" alt=\"Michigan Police Sergeant Doesn&#x27;t Know The Law\">\n    </a>\n    <figcaption>Michigan Police Sergeant Doesn&#x27;t Know The Law</figcaption>\n  </figure>\n  <p><a href=\"https://www.youtube.com/watch?v=6wsDmZo9UMI\" title=\"Michigan Police Sergeant Doesn&#x27;t Know The Law\">Play Video</a></p>\n</div>\n<div class=\"section yt\">\n  <header>\n    <h2>Don&#x27;t Talk to the Police</h2>\n  </header>\n  <figure>\n    <a href=\"https://www.youtube.com/watch?v=d-7o9xYp7eE\" class=\"no-tufte-underline\" title=\"Don&#x27;t Talk to the Police\">\n      <img src=\"/image/yid-d-7o9xYp7eE.jpg\" alt=\"Don&#x27;t Talk to the Police\">\n    </a>\n    <figcaption>Don&#x27;t Talk to the Police</figcaption>\n  </figure>\n  <p><a href=\"https://www.youtube.com/watch?v=d-7o9xYp7eE\" title=\"Don&#x27;t Talk to the Police\">Play Video</a></p>\n</div>\n<div class=\"section yt\">\n  <header>\n    <h2>How to make a simple $7 IMSI Catcher</h2>\n  </header>\n  <figure>\n    <a href=\"https://www.youtube.com/watch?v=UjwgNd_as30\" class=\"no-tufte-underline\" title=\"How to make a simple $7 IMSI Catcher\">\n      <img src=\"/image/yid-UjwgNd_as30.jpg\" alt=\"How to make a simple $7 IMSI Catcher\">\n    </a>\n    <figcaption>How to make a simple $7 IMSI Catcher</figcaption>\n  </figure>\n  <p><a href=\"https://www.youtube.com/watch?v=UjwgNd_as30\" title=\"How to make a simple $7 IMSI Catcher\">Play Video</a></p>\n</div>\n<div class=\"section yt\">\n  <header>\n    <h2>Catching IMSI Catchers</h2>\n  </header>\n  <figure>\n    <a href=\"https://www.youtube.com/watch?v=eivHO1OzF5E\" class=\"no-tufte-underline\" title=\"Catching IMSI Catchers\">\n      <img src=\"/image/yid-eivHO1OzF5E.jpg\" alt=\"Catching IMSI Catchers\">\n    </a>\n    <figcaption>Catching IMSI Catchers</figcaption>\n  </figure>\n  <p><a href=\"https://www.youtube.com/watch?v=eivHO1OzF5E\" title=\"Catching IMSI Catchers\">Play Video</a></p>\n</div>\n<div class=\"section yt\">\n  <header>\n    <h2>Project Overwatch: Multinational Effort to Combat IMSI Catchers (Intercept SMS And Track Location For $7)</h2>\n  </header>\n  <figure>\n    <a href=\"https://www.youtube.com/watch?v=UG5juhuhE2g\" class=\"no-tufte-underline\" title=\"Project Overwatch: Multinational Effort to Combat IMSI Catchers (Intercept SMS And Track Location For $7)\">\n      <img src=\"/image/yid-UG5juhuhE2g.jpg\" alt=\"Project Overwatch: Multinational Effort to Combat IMSI Catchers (Intercept SMS And Track Location For $7)\">\n    </a>\n    <figcaption>Project Overwatch: Multinational Effort to Combat IMSI Catchers (Intercept SMS And Track Location For $7)</figcaption>\n  </figure>\n  <p><a href=\"https://www.youtube.com/watch?v=UG5juhuhE2g\" title=\"Project Overwatch: Multinational Effort to Combat IMSI Catchers (Intercept SMS And Track Location For $7)\">Play Video</a></p>\n</div>\n<div class=\"section yt\">\n  <header>\n    <h2>BSIDES CPT 2019 - Hacking satellites with Software Defined Radio (SDR) - Gerard de Jong</h2>\n  </header>\n  <figure>\n    <a href=\"https://www.youtube.com/watch?v=gMwciWchH3Q\" class=\"no-tufte-underline\" title=\"BSIDES CPT 2019 - Hacking satellites with Software Defined Radio (SDR) - Gerard de Jong\">\n      <img src=\"/image/yid-gMwciWchH3Q.jpg\" alt=\"BSIDES CPT 2019 - Hacking satellites with Software Defined Radio (SDR) - Gerard de Jong\">\n    </a>\n    <figcaption>BSIDES CPT 2019 - Hacking satellites with Software Defined Radio (SDR) - Gerard de Jong</figcaption>\n  </figure>\n  <p><a href=\"https://www.youtube.com/watch?v=gMwciWchH3Q\" title=\"BSIDES CPT 2019 - Hacking satellites with Software Defined Radio (SDR) - Gerard de Jong\">Play Video</a></p>\n</div>\n<div class=\"section yt\">\n  <header>\n    <h2>The Coolest Radio You&#x27;ve Probably Never Heard Of</h2>\n  </header>\n  <figure>\n    <a href=\"https://www.youtube.com/watch?v=h4x7cGALaC8&t=61\" class=\"no-tufte-underline\" title=\"The Coolest Radio You&#x27;ve Probably Never Heard Of\">\n      <img src=\"/image/yid-h4x7cGALaC8.jpg\" alt=\"The Coolest Radio You&#x27;ve Probably Never Heard Of\">\n    </a>\n    <figcaption>The Coolest Radio You&#x27;ve Probably Never Heard Of</figcaption>\n  </figure>\n  <p><a href=\"https://www.youtube.com/watch?v=h4x7cGALaC8&t=61\" title=\"The Coolest Radio You&#x27;ve Probably Never Heard Of\">Play Video</a></p>\n</div>\n<div class=\"section yt\">\n  <header>\n    <h2>Locating Cellular Signal with HackRF Spectrum Analyzer SDR Software</h2>\n  </header>\n  <figure>\n    <a href=\"https://www.youtube.com/watch?v=aFHWAEb3sn4\" class=\"no-tufte-underline\" title=\"Locating Cellular Signal with HackRF Spectrum Analyzer SDR Software\">\n      <img src=\"/image/yid-aFHWAEb3sn4.jpg\" alt=\"Locating Cellular Signal with HackRF Spectrum Analyzer SDR Software\">\n    </a>\n    <figcaption>Locating Cellular Signal with HackRF Spectrum Analyzer SDR Software</figcaption>\n  </figure>\n  <p><a href=\"https://www.youtube.com/watch?v=aFHWAEb3sn4\" title=\"Locating Cellular Signal with HackRF Spectrum Analyzer SDR Software\">Play Video</a></p>\n</div>\n<div class=\"section yt\">\n  <header>\n    <h2>How Telephone Phreaking Worked (Starts at 4:30)</h2>\n  </header>\n  <figure>\n    <a href=\"https://www.youtube.com/watch?v=4tHyZdtXULw\" class=\"no-tufte-underline\" title=\"How Telephone Phreaking Worked (Starts at 4:30)\">\n      <img src=\"/image/yid-4tHyZdtXULw.jpg\" alt=\"How Telephone Phreaking Worked (Starts at 4:30)\">\n    </a>\n    <figcaption>How Telephone Phreaking Worked (Starts at 4:30)</figcaption>\n  </figure>\n  <p><a href=\"https://www.youtube.com/watch?v=4tHyZdtXULw\" title=\"How Telephone Phreaking Worked (Starts at 4:30)\">Play Video</a></p>\n</div>\n<div class=\"section yt\">\n  <header>\n    <h2>Hackers The History Of Hacking - Phone Phreaking, Cap.Crunch, Wozniak, Mitnick</h2>\n  </header>\n  <figure>\n    <a href=\"https://www.youtube.com/watch?v=FufYSx2_6Bg\" class=\"no-tufte-underline\" title=\"Hackers The History Of Hacking - Phone Phreaking, Cap.Crunch, Wozniak, Mitnick\">\n      <img src=\"/image/yid-FufYSx2_6Bg.jpg\" alt=\"Hackers The History Of Hacking - Phone Phreaking, Cap.Crunch, Wozniak, Mitnick\">\n    </a>\n    <figcaption>Hackers The History Of Hacking - Phone Phreaking, Cap.Crunch, Wozniak, Mitnick</figcaption>\n  </figure>\n  <p><a href=\"https://www.youtube.com/watch?v=FufYSx2_6Bg\" title=\"Hackers The History Of Hacking - Phone Phreaking, Cap.Crunch, Wozniak, Mitnick\">Play Video</a></p>\n</div>\n<div class=\"section yt\">\n  <header>\n    <h2>Dutch Hacker Attacking Pentagon via FTP (1991)</h2>\n  </header>\n  <figure>\n    <a href=\"https://www.youtube.com/watch?v=3ZU2DHcjrcI\" class=\"no-tufte-underline\" title=\"Dutch Hacker Attacking Pentagon via FTP (1991)\">\n      <img src=\"/image/yid-3ZU2DHcjrcI.jpg\" alt=\"Dutch Hacker Attacking Pentagon via FTP (1991)\">\n    </a>\n    <figcaption>Dutch Hacker Attacking Pentagon via FTP (1991)</figcaption>\n  </figure>\n  <p><a href=\"https://www.youtube.com/watch?v=3ZU2DHcjrcI\" title=\"Dutch Hacker Attacking Pentagon via FTP (1991)\">Play Video</a></p>\n</div>\n<div class=\"section yt\">\n  <header>\n    <h2>The Jerky Boys - Piano Tuner</h2>\n  </header>\n  <figure>\n    <a href=\"https://www.youtube.com/watch?v=eajkTddpeQQ\" class=\"no-tufte-underline\" title=\"The Jerky Boys - Piano Tuner\">\n      <img src=\"/image/yid-eajkTddpeQQ.jpg\" alt=\"The Jerky Boys - Piano Tuner\">\n    </a>\n    <figcaption>The Jerky Boys - Piano Tuner</figcaption>\n  </figure>\n  <p><a href=\"https://www.youtube.com/watch?v=eajkTddpeQQ\" title=\"The Jerky Boys - Piano Tuner\">Play Video</a></p>\n</div>\n<div class=\"section yt\">\n  <header>\n    <h2>Jerky Boys - Sol Rosenberg&#x27;s Glasses</h2>\n  </header>\n  <figure>\n    <a href=\"https://www.youtube.com/watch?v=jF0ajgT_09s\" class=\"no-tufte-underline\" title=\"Jerky Boys - Sol Rosenberg&#x27;s Glasses\">\n      <img src=\"/image/yid-jF0ajgT_09s.jpg\" alt=\"Jerky Boys - Sol Rosenberg&#x27;s Glasses\">\n    </a>\n    <figcaption>Jerky Boys - Sol Rosenberg&#x27;s Glasses</figcaption>\n  </figure>\n  <p><a href=\"https://www.youtube.com/watch?v=jF0ajgT_09s\" title=\"Jerky Boys - Sol Rosenberg&#x27;s Glasses\">Play Video</a></p>\n</div>\n<div class=\"section yt\">\n  <header>\n    <h2>The Jerky Boys - Drinking Problem</h2>\n  </header>\n  <figure>\n    <a href=\"https://www.youtube.com/watch?v=ZllDjMXSjOE\" class=\"no-tufte-underline\" title=\"The Jerky Boys - Drinking Problem\">\n      <img src=\"/image/yid-ZllDjMXSjOE.jpg\" alt=\"The Jerky Boys - Drinking Problem\">\n    </a>\n    <figcaption>The Jerky Boys - Drinking Problem</figcaption>\n  </figure>\n  <p><a href=\"https://www.youtube.com/watch?v=ZllDjMXSjOE\" title=\"The Jerky Boys - Drinking Problem\">Play Video</a></p>\n</div>\n<div class=\"section yt\">\n  <header>\n    <h2>Cact-Eye Hidden Camera Prank Calls</h2>\n  </header>\n  <figure>\n    <a href=\"https://www.youtube.com/watch?v=p1kWQOa-ULM\" class=\"no-tufte-underline\" title=\"Cact-Eye Hidden Camera Prank Calls\">\n      <img src=\"/image/yid-p1kWQOa-ULM.jpg\" alt=\"Cact-Eye Hidden Camera Prank Calls\">\n    </a>\n    <figcaption>Cact-Eye Hidden Camera Prank Calls</figcaption>\n  </figure>\n  <p><a href=\"https://www.youtube.com/watch?v=p1kWQOa-ULM\" title=\"Cact-Eye Hidden Camera Prank Calls\">Play Video</a></p>\n</div>\n<div class=\"section yt\">\n  <header>\n    <h2>Radio and Swap Shop Prank Calls</h2>\n  </header>\n  <figure>\n    <a href=\"https://www.youtube.com/watch?v=kHA79JHGlOk\" class=\"no-tufte-underline\" title=\"Radio and Swap Shop Prank Calls\">\n      <img src=\"/image/yid-kHA79JHGlOk.jpg\" alt=\"Radio and Swap Shop Prank Calls\">\n    </a>\n    <figcaption>Radio and Swap Shop Prank Calls</figcaption>\n  </figure>\n  <p><a href=\"https://www.youtube.com/watch?v=kHA79JHGlOk\" title=\"Radio and Swap Shop Prank Calls\">Play Video</a></p>\n</div>\n<div class=\"section yt\">\n  <header>\n    <h2>Tour of the Cacti Radio Studio</h2>\n  </header>\n  <figure>\n    <a href=\"https://www.youtube.com/watch?v=Q1YBk6tbM8s\" class=\"no-tufte-underline\" title=\"Tour of the Cacti Radio Studio\">\n      <img src=\"/image/yid-Q1YBk6tbM8s.jpg\" alt=\"Tour of the Cacti Radio Studio\">\n    </a>\n    <figcaption>Tour of the Cacti Radio Studio</figcaption>\n  </figure>\n  <p><a href=\"https://www.youtube.com/watch?v=Q1YBk6tbM8s\" title=\"Tour of the Cacti Radio Studio\">Play Video</a></p>\n</div>\n<div class=\"section yt\">\n  <header>\n    <h2>Pump Up The Volume</h2>\n  </header>\n  <figure>\n    <a href=\"https://www.youtube.com/watch?v=uo-km-qfJe8\" class=\"no-tufte-underline\" title=\"Pump Up The Volume\">\n      <img src=\"/image/yid-uo-km-qfJe8.jpg\" alt=\"Pump Up The Volume\">\n    </a>\n    <figcaption>Pump Up The Volume</figcaption>\n  </figure>\n  <p><a href=\"https://www.youtube.com/watch?v=uo-km-qfJe8\" title=\"Pump Up The Volume\">Play Video</a></p>\n</div>\n<div class=\"section yt\">\n  <header>\n    <h2>Classroom Craziness Compilation</h2>\n  </header>\n  <figure>\n    <a href=\"https://www.youtube.com/watch?v=lwEFEIxcj4Q\" class=\"no-tufte-underline\" title=\"Classroom Craziness Compilation\">\n      <img src=\"/image/yid-lwEFEIxcj4Q.jpg\" alt=\"Classroom Craziness Compilation\">\n    </a>\n    <figcaption>Classroom Craziness Compilation</figcaption>\n  </figure>\n  <p><a href=\"https://www.youtube.com/watch?v=lwEFEIxcj4Q\" title=\"Classroom Craziness Compilation\">Play Video</a></p>\n</div>\n<div class=\"section yt\">\n  <header>\n    <h2>*Trance* Orbital - Halcyon and On and On ( Hackers / 1995 )</h2>\n  </header>\n  <figure>\n    <a href=\"https://www.youtube.com/watch?v=33WuGp6fs3s\" class=\"no-tufte-underline\" title=\"*Trance* Orbital - Halcyon and On and On ( Hackers / 1995 )\">\n      <img src=\"/image/yid-33WuGp6fs3s.jpg\" alt=\"*Trance* Orbital - Halcyon and On and On ( Hackers / 1995 )\">\n    </a>\n    <figcaption>*Trance* Orbital - Halcyon and On and On ( Hackers / 1995 )</figcaption>\n  </figure>\n  <p><a href=\"https://www.youtube.com/watch?v=33WuGp6fs3s\" title=\"*Trance* Orbital - Halcyon and On and On ( Hackers / 1995 )\">Play Video</a></p>\n</div>\n<div class=\"section yt\">\n  <header>\n    <h2>The Conscience of a Hacker</h2>\n  </header>\n  <figure>\n    <a href=\"https://www.youtube.com/watch?v=0tEnnvZbYek\" class=\"no-tufte-underline\" title=\"The Conscience of a Hacker\">\n      <img src=\"/image/yid-0tEnnvZbYek.jpg\" alt=\"The Conscience of a Hacker\">\n    </a>\n    <figcaption>The Conscience of a Hacker</figcaption>\n  </figure>\n  <p><a href=\"https://www.youtube.com/watch?v=0tEnnvZbYek\" title=\"The Conscience of a Hacker\">Play Video</a></p>\n</div>",
  "print": "<div class=\"section yt avoid-break-inside\" style=\"padding-bottom: 2rem;\">\n  <span>Steve Jobs Interview about the Blue Box Story<sup>[1]</sup></span>\n</div>\n<div class=\"section yt avoid-break-inside\" style=\"padding-bottom: 2rem;\">\n  <span>Blue Box | Homemade Replica Blue Box For Phone Phreaking<sup>[2]</sup></span>\n</div>\n<div class=\"section yt avoid-break-inside\" style=\"padding-bottom: 2rem;\">\n  <span>20th Anniversary Redbox Radioshack tone dialer EC-389 Catalog no 65-721<sup>[3]</sup></span>\n</div>\n<div class=\"section yt avoid-break-inside\" style=\"padding-bottom: 2rem;\">\n  <span>Oldschool Radioshack Redbox pocket tone dialer<sup>[4]</sup></span>\n</div>\n<div class=\"section yt avoid-break-inside\" style=\"padding-bottom: 2rem;\">\n  <span>Emmanuel Goldstein, sock puppet Q&A<sup>[5]</sup></span>\n</div>\n<div class=\"section yt avoid-break-inside\" style=\"padding-bottom: 2rem;\">\n  <span>Phiber Optik - Last Interview Before 1 Year In Prison (1993)<sup>[6]</sup></span>\n</div>\n<div class=\"section yt avoid-break-inside\" style=\"padding-bottom: 2rem;\">\n  <span>Joybubbles ❤️<sup>[7]</sup></span>\n</div>\n<div class=\"section yt avoid-break-inside\" style=\"padding-bottom: 2rem;\">\n  <span>Covid Crops Prank Call<sup>[8]</sup></span>\n</div>\n<div class=\"section yt avoid-break-inside\" style=\"padding-bottom: 2rem;\">\n  <span>Harassing Black Friday Wal-Mart Customers with Prank Calls<sup>[9]</sup></span>\n</div>\n<div class=\"section yt avoid-break-inside\" style=\"padding-bottom: 2rem;\">\n  <span>The Last HOPE (2008) - The Art of Social Engineering<sup>[10]</sup></span>\n</div>\n<div class=\"section yt avoid-break-inside\" style=\"padding-bottom: 2rem;\">\n  <span>Phone Phreak Captain Crunch Rare Interview from '78<sup>[11]</sup></span>\n</div>\n<div class=\"section yt avoid-break-inside\" style=\"padding-bottom: 2rem;\">\n  <span>2600 Interview with Kevin Mitnick<sup>[12]</sup></span>\n</div>\n<div class=\"section yt avoid-break-inside\" style=\"padding-bottom: 2rem;\">\n  <span>L0pht Heavy Industries<sup>[13]</sup></span>\n</div>\n<div class=\"section yt avoid-break-inside\" style=\"padding-bottom: 2rem;\">\n  <span>Amazon gave Ring video to police without user’s permission (FOR ANY PURPOSE!)<sup>[14]</sup></span>\n</div>\n<div class=\"section yt avoid-break-inside\" style=\"padding-bottom: 2rem;\">\n  <span>48 Dirty Little Secrets Cryptographers Don’t Want You To Know<sup>[15]</sup></span>\n</div>\n<div class=\"section yt avoid-break-inside\" style=\"padding-bottom: 2rem;\">\n  <span>Broadpwn: Remotely Compromising Android and iOS via a Bug in Broadcom's Wi-Fi Chipsets<sup>[16]</sup></span>\n</div>\n<div class=\"section yt avoid-break-inside\" style=\"padding-bottom: 2rem;\">\n  <span>Police are tracking you and your license plates<sup>[17]</sup></span>\n</div>\n<div class=\"section yt avoid-break-inside\" style=\"padding-bottom: 2rem;\">\n  <span>The Stingray: How Law Enforcement Can Track Your Every Move<sup>[18]</sup></span>\n</div>\n<div class=\"section yt avoid-break-inside\" style=\"padding-bottom: 2rem;\">\n  <span>What Are My Rights With Police? (When I Get Pulled Over)<sup>[19]</sup></span>\n</div>\n<div class=\"section yt avoid-break-inside\" style=\"padding-bottom: 2rem;\">\n  <span>Michigan Police Sergeant Doesn't Know The Law<sup>[20]</sup></span>\n</div>\n<div class=\"section yt avoid-break-inside\" style=\"padding-bottom: 2rem;\">\n  <span>Don't Talk to the Police<sup>[21]</sup></span>\n</div>\n<div class=\"section yt avoid-break-inside\" style=\"padding-bottom: 2rem;\">\n  <span>How to make a simple $7 IMSI Catcher<sup>[22]</sup></span>\n</div>\n<div class=\"section yt avoid-break-inside\" style=\"padding-bottom: 2rem;\">\n  <span>Catching IMSI Catchers<sup>[23]</sup></span>\n</div>\n<div class=\"section yt avoid-break-inside\" style=\"padding-bottom: 2rem;\">\n  <span>Project Overwatch: Multinational Effort to Combat IMSI Catchers (Intercept SMS And Track Location For $7)<sup>[24]</sup></span>\n</div>\n<div class=\"section yt avoid-break-inside\" style=\"padding-bottom: 2rem;\">\n  <span>BSIDES CPT 2019 - Hacking satellites with Software Defined Radio (SDR) - Gerard de Jong<sup>[25]</sup></span>\n</div>\n<div class=\"section yt avoid-break-inside\" style=\"padding-bottom: 2rem;\">\n  <span>The Coolest Radio You've Probably Never Heard Of<sup>[26]</sup></span>\n</div>\n<div class=\"section yt avoid-break-inside\" style=\"padding-bottom: 2rem;\">\n  <span>Locating Cellular Signal with HackRF Spectrum Analyzer SDR Software<sup>[27]</sup></span>\n</div>\n<div class=\"section yt avoid-break-inside\" style=\"padding-bottom: 2rem;\">\n  <span>How Telephone Phreaking Worked (Starts at 4:30)<sup>[28]</sup></span>\n</div>\n<div class=\"section yt avoid-break-inside\" style=\"padding-bottom: 2rem;\">\n  <span>Hackers The History Of Hacking - Phone Phreaking, Cap.Crunch, Wozniak, Mitnick<sup>[29]</sup></span>\n</div>\n<div class=\"section yt avoid-break-inside\" style=\"padding-bottom: 2rem;\">\n  <span>Dutch Hacker Attacking Pentagon via FTP (1991)<sup>[30]</sup></span>\n</div>\n<div class=\"section yt avoid-break-inside\" style=\"padding-bottom: 2rem;\">\n  <span>The Jerky Boys - Piano Tuner<sup>[31]</sup></span>\n</div>\n<div class=\"section yt avoid-break-inside\" style=\"padding-bottom: 2rem;\">\n  <span>Jerky Boys - Sol Rosenberg's Glasses<sup>[32]</sup></span>\n</div>\n<div class=\"section yt avoid-break-inside\" style=\"padding-bottom: 2rem;\">\n  <span>The Jerky Boys - Drinking Problem<sup>[33]</sup></span>\n</div>\n<div class=\"section yt avoid-break-inside\" style=\"padding-bottom: 2rem;\">\n  <span>Cact-Eye Hidden Camera Prank Calls<sup>[34]</sup></span>\n</div>\n<div class=\"section yt avoid-break-inside\" style=\"padding-bottom: 2rem;\">\n  <span>Radio and Swap Shop Prank Calls<sup>[35]</sup></span>\n</div>\n<div class=\"section yt avoid-break-inside\" style=\"padding-bottom: 2rem;\">\n  <span>Tour of the Cacti Radio Studio<sup>[36]</sup></span>\n</div>\n<div class=\"section yt avoid-break-inside\" style=\"padding-bottom: 2rem;\">\n  <span>Pump Up The Volume<sup>[37]</sup></span>\n</div>\n<div class=\"section yt avoid-break-inside\" style=\"padding-bottom: 2rem;\">\n  <span>Classroom Craziness Compilation<sup>[38]</sup></span>\n</div>\n<div class=\"section yt avoid-break-inside\" style=\"padding-bottom: 2rem;\">\n  <span>*Trance* Orbital - Halcyon and On and On ( Hackers / 1995 )<sup>[39]</sup></span>\n</div>\n<div class=\"section yt avoid-break-inside\" style=\"padding-bottom: 2rem;\">\n  <span>The Conscience of a Hacker<sup>[40]</sup></span>\n</div>\n<div class=\"break-after\">&nbsp;</div>\n<div>\n  <div class=\"section\" style=\"padding-bottom: 1rem;\">References</div>\n  <div>[1]: https://www.youtube.com/watch?v=HFURM8O-oYI&t=13</div>\n  <div>[2]: https://www.youtube.com/watch?v=CRp8XvwNSD0</div>\n  <div>[3]: https://www.youtube.com/watch?v=JAj0BMIODWo</div>\n  <div>[4]: https://www.youtube.com/watch?v=AXZMgHKhefk</div>\n  <div>[5]: https://www.youtube.com/watch?v=AJir12xkUY4</div>\n  <div>[6]: https://www.youtube.com/watch?v=hkQ0BOrFTJk</div>\n  <div>[7]: https://www.youtube.com/watch?v=vVZm7I1CTBs</div>\n  <div>[8]: https://www.youtube.com/watch?v=jG1T34uE58o</div>\n  <div>[9]: https://www.youtube.com/watch?v=RGmdwiz9zDE</div>\n  <div>[10]: https://www.youtube.com/watch?v=1M9pwYQSbQU</div>\n  <div>[11]: https://www.youtube.com/watch?v=n6TjjE8NHV0</div>\n  <div>[12]: https://www.youtube.com/watch?v=6OJyaML7_rw</div>\n  <div>[13]: https://www.youtube.com/watch?v=VVJldn_MmMY</div>\n  <div>[14]: https://www.youtube.com/watch?v=utPRvqhXfoo</div>\n  <div>[15]: https://www.youtube.com/watch?v=iZa_XKpj9X4</div>\n  <div>[16]: https://www.youtube.com/watch?v=TDk2RId8LFo</div>\n  <div>[17]: https://www.youtube.com/watch?v=DH7edXaZS0A</div>\n  <div>[18]: https://www.youtube.com/watch?v=wzSgLpNrr2E</div>\n  <div>[19]: https://www.youtube.com/watch?v=f26QJKREYB8&t=44</div>\n  <div>[20]: https://www.youtube.com/watch?v=6wsDmZo9UMI</div>\n  <div>[21]: https://www.youtube.com/watch?v=d-7o9xYp7eE</div>\n  <div>[22]: https://www.youtube.com/watch?v=UjwgNd_as30</div>\n  <div>[23]: https://www.youtube.com/watch?v=eivHO1OzF5E</div>\n  <div>[24]: https://www.youtube.com/watch?v=UG5juhuhE2g</div>\n  <div>[25]: https://www.youtube.com/watch?v=gMwciWchH3Q</div>\n  <div>[26]: https://www.youtube.com/watch?v=h4x7cGALaC8&t=61</div>\n  <div>[27]: https://www.youtube.com/watch?v=aFHWAEb3sn4</div>\n  <div>[28]: https://www.youtube.com/watch?v=4tHyZdtXULw</div>\n  <div>[29]: https://www.youtube.com/watch?v=FufYSx2_6Bg</div>\n  <div>[30]: https://www.youtube.com/watch?v=3ZU2DHcjrcI</div>\n  <div>[31]: https://www.youtube.com/watch?v=eajkTddpeQQ</div>\n  <div>[32]: https://www.youtube.com/watch?v=jF0ajgT_09s</div>\n  <div>[33]: https://www.youtube.com/watch?v=ZllDjMXSjOE</div>\n  <div>[34]: https://www.youtube.com/watch?v=p1kWQOa-ULM</div>\n  <div>[35]: https://www.youtube.com/watch?v=kHA79JHGlOk</div>\n  <div>[36]: https://www.youtube.com/watch?v=Q1YBk6tbM8s</div>\n  <div>[37]: https://www.youtube.com/watch?v=uo-km-qfJe8</div>\n  <div>[38]: https://www.youtube.com/watch?v=lwEFEIxcj4Q</div>\n  <div>[39]: https://www.youtube.com/watch?v=33WuGp6fs3s</div>\n  <div>[40]: https://www.youtube.com/watch?v=0tEnnvZbYek</div>\n</div>",
  "bootstrap": "<div class=\"card card-section bg-dark text-warning shadow\">\n  <div class=\"card-header\">Steve Jobs Interview about the Blue Box Story</div>\n  <a href=\"https://www.youtube.com/watch?v=HFURM8O-oYI&t=13\" title=\"Steve Jobs Interview about the Blue Box Story\" alt=\"Steve Jobs Interview about the Blue Box Story\"><img src=\"/image/yid-HFURM8O-oYI.jpg\" alt=\"Steve Jobs Interview about the Blue Box Story\" class=\"card-img\"></a>\n  <div class=\"card-body\">\n    <a href=\"https://www.youtube.com/watch?v=HFURM8O-oYI&t=13\" title=\"Steve Jobs Interview about the Blue Box Story\" class=\"btn btn-warning\">Play Video</a>\n  </div>\n</div>\n<div class=\"card card-section bg-dark text-warning shadow\">\n  <div class=\"card-header\">Blue Box | Homemade Replica Blue Box For Phone Phreaking</div>\n  <a href=\"https://www.youtube.com/watch?v=CRp8XvwNSD0\" title=\"Blue Box | Homemade Replica Blue Box For Phone Phreaking\" alt=\"Blue Box | Homemade Replica Blue Box For Phone Phreaking\"><img src=\"/image/yid-CRp8XvwNSD0.jpg\" alt=\"Blue Box | Homemade Replica Blue Box For Phone Phreaking\" class=\"card-img\"></a>\n  <div class=\"card-body\">\n    <a href=\"https://www.youtube.com/watch?v=CRp8XvwNSD0\" title=\"Blue Box | Homemade Replica Blue Box For Phone Phreaking\" class=\"btn btn-warning\">Play Video</a>\n  </div>\n</div>\n<div class=\"card card-section bg-dark text-warning shadow\">\n  <div class=\"card-header\">20th Anniversary Redbox Radioshack tone dialer EC-389 Catalog no 65-721</div>\n  <a href=\"https://www.youtube.com/watch?v=JAj0BMIODWo\" title=\"20th Anniversary Redbox Radioshack tone dialer EC-389 Catalog no 65-721\" alt=\"20th Anniversary Redbox Radioshack tone dialer EC-389 Catalog no 65-721\"><img src=\"/image/yid-JAj0BMIODWo.jpg\" alt=\"20th Anniversary Redbox Radioshack tone dialer EC-389 Catalog no 65-721\" class=\"card-img\"></a>\n  <div class=\"card-body\">\n    <a href=\"https://www.youtube.com/watch?v=JAj0BMIODWo\" title=\"20th Anniversary Redbox Radioshack tone dialer EC-389 Catalog no 65-721\" class=\"btn btn-warning\">Play Video</a>\n  </div>\n</div>\n<div class=\"card card-section bg-dark text-warning shadow\">\n  <div class=\"card-header\">Oldschool Radioshack Redbox pocket tone dialer</div>\n  <a href=\"https://www.youtube.com/watch?v=AXZMgHKhefk\" title=\"Oldschool Radioshack Redbox pocket tone dialer\" alt=\"Oldschool Radioshack Redbox pocket tone dialer\"><img src=\"/image/yid-AXZMgHKhefk.jpg\" alt=\"Oldschool Radioshack Redbox pocket tone dialer\" class=\"card-img\"></a>\n  <div class=\"card-body\">\n    <a href=\"https://www.youtube.com/watch?v=AXZMgHKhefk\" title=\"Oldschool Radioshack Redbox pocket tone dialer\" class=\"btn btn-warning\">Play Video</a>\n  </div>\n</div>\n<div class=\"card card-section bg-dark text-warning shadow\">\n  <div class=\"card-header\">Emmanuel Goldstein, sock puppet Q&amp;A</div>\n  <a href=\"https://www.youtube.com/watch?v=AJir12xkUY4\" title=\"Emmanuel Goldstein, sock puppet Q&amp;A\" alt=\"Emmanuel Goldstein, sock puppet Q&amp;A\"><img src=\"/image/yid-AJir12xkUY4.jpg\" alt=\"Emmanuel Goldstein, sock puppet Q&amp;A\" class=\"card-img\"></a>\n  <div class=\"card-body\">\n    <a href=\"https://www.youtube.com/watch?v=AJir12xkUY4\" title=\"Emmanuel Goldstein, sock puppet Q&amp;A\" class=\"btn btn-warning\">Play Video</a>\n  </div>\n</div>\n<div class=\"card card-section bg-dark text-warning shadow\">\n  <div class=\"card-header\">Phiber Optik - Last Interview Before 1 Year In Prison (1993)</div>\n  <a href=\"https://www.youtube.com/watch?v=hkQ0BOrFTJk\" title=\"Phiber Optik - Last Interview Before 1 Year In Prison (1993)\" alt=\"Phiber Optik - Last Interview Before 1 Year In Prison (1993)\"><img src=\"/image/yid-hkQ0BOrFTJk.jpg\" alt=\"Phiber Optik - Last Interview Before 1 Year In Prison (1993)\" class=\"card-img\"></a>\n  <div class=\"card-body\">\n    <a href=\"https://www.youtube.com/watch?v=hkQ0BOrFTJk\" title=\"Phiber Optik - Last Interview Before 1 Year In Prison (1993)\" class=\"btn btn-warning\">Play Video</a>\n  </div>\n</div>\n<div class=\"card card-section bg-dark text-warning shadow\">\n  <div class=\"card-header\">Joybubbles ❤️</div>\n  <a href=\"https://www.youtube.com/watch?v=vVZm7I1CTBs\" title=\"Joybubbles ❤️\" alt=\"Joybubbles ❤️\"><img src=\"/image/yid-vVZm7I1CTBs.jpg\" alt=\"Joybubbles ❤️\" class=\"card-img\"></a>\n  <div class=\"card-body\">\n    <a href=\"https://www.youtube.com/watch?v=vVZm7I1CTBs\" title=\"Joybubbles ❤️\" class=\"btn btn-warning\">Play Video</a>\n  </div>\n</div>\n<div class=\"card card-section bg-dark text-warning shadow\">\n  <div class=\"card-header\">Covid Crops Prank Call</div>\n  <a href=\"https://www.youtube.com/watch?v=jG1T34uE58o\" title=\"Covid Crops Prank Call\" alt=\"Covid Crops Prank Call\"><img src=\"/image/yid-jG1T34uE58o.jpg\" alt=\"Covid Crops Prank Call\" class=\"card-img\"></a>\n  <div class=\"card-body\">\n    <a href=\"https://www.youtube.com/watch?v=jG1T34uE58o\" title=\"Covid Crops Prank Call\" class=\"btn btn-warning\">Play Video</a>\n  </div>\n</div>\n<div class=\"card card-section bg-dark text-warning shadow\">\n  <div class=\"card-header\">Harassing Black Friday Wal-Mart Customers with Prank Calls</div>\n  <a href=\"https://www.youtube.com/watch?v=RGmdwiz9zDE\" title=\"Harassing Black Friday Wal-Mart Customers with Prank Calls\" alt=\"Harassing Black Friday Wal-Mart Customers with Prank Calls\"><img src=\"/image/yid-RGmdwiz9zDE.jpg\" alt=\"Harassing Black Friday Wal-Mart Customers with Prank Calls\" class=\"card-img\"></a>\n  <div class=\"card-body\">\n    <a href=\"https://www.youtube.com/watch?v=RGmdwiz9zDE\" title=\"Harassing Black Friday Wal-Mart Customers with Prank Calls\" class=\"btn btn-warning\">Play Video</a>\n  </div>\n</div>\n<div class=\"card card-section bg-dark text-warning shadow\">\n  <div class=\"card-header\">The Last HOPE (2008) - The Art of Social Engineering</div>\n  <a href=\"https://www.youtube.com/watch?v=1M9pwYQSbQU\" title=\"The Last HOPE (2008) - The Art of Social Engineering\" alt=\"The Last HOPE (2008) - The Art of Social Engineering\"><img src=\"/image/yid-1M9pwYQSbQU.jpg\" alt=\"The Last HOPE (2008) - The Art of Social Engineering\" class=\"card-img\"></a>\n  <div class=\"card-body\">\n    <a href=\"https://www.youtube.com/watch?v=1M9pwYQSbQU\" title=\"The Last HOPE (2008) - The Art of Social Engineering\" class=\"btn btn-warning\">Play Video</a>\n  </div>\n</div>\n<div class=\"card card-section bg-dark text-warning shadow\">\n  <div class=\"card-header\">Phone Phreak Captain Crunch Rare Interview from &#x27;78</div>\n  <a href=\"https://www.youtube.com/watch?v=n6TjjE8NHV0\" title=\"Phone Phreak Captain Crunch Rare Interview from &#x27;78\" alt=\"Phone Phreak Captain Crunch Rare Interview from &#x27;78\"><img src=\"/image/yid-n6TjjE8NHV0.jpg\" alt=\"Phone Phreak Captain Crunch Rare Interview from &#x27;78\" class=\"card-img\"></a>\n  <div class=\"card-body\">\n    <a href=\"https://www.youtube.com/watch?v=n6TjjE8NHV0\" title=\"Phone Phreak Captain Crunch Rare Interview from &#x27;78\" class=\"btn btn-warning\">Play Video</a>\n  </div>\n</div>\n<div class=\"card card-section bg-dark text-warning shadow\">\n  <div class=\"card-header\">2600 Interview with Kevin Mitnick</div>\n  <a href=\"https://www.youtube.com/watch?v=6OJyaML7_rw\" title=\"2600 Interview with Kevin Mitnick\" alt=\"2600 Interview with Kevin Mitnick\"><img src=\"/image/yid-6OJyaML7_rw.jpg\" alt=\"2600 Interview with Kevin Mitnick\" class=\"card-img\"></a>\n  <div class=\"card-body\">\n    <a href=\"https://www.youtube.com/watch?v=6OJyaML7_rw\" title=\"2600 Interview with Kevin Mitnick\" class=\"btn btn-warning\">Play Video</a>\n  </div>\n</div>\n<div class=\"card card-section bg-dark text-warning shadow\">\n  <div class=\"card-header\">L0pht Heavy Industries</div>\n  <a href=\"https://www.youtube.com/watch?v=VVJldn_MmMY\" title=\"L0pht Heavy Industries\" alt=\"L0pht Heavy Industries\"><img src=\"/image/yid-VVJldn_MmMY.jpg\" alt=\"L0pht Heavy Industries\" class=\"card-img\"></a>\n  <div class=\"card-body\">\n    <a href=\"https://www.youtube.com/watch?v=VVJldn_MmMY\" title=\"L0pht Heavy Industries\" class=\"btn btn-warning\">Play Video</a>\n  </div>\n</div>\n<div class=\"card card-section bg-dark text-warning shadow\">\n  <div class=\"card-header\">Amazon gave Ring video to police without user’s permission (FOR ANY PURPOSE!)</div>\n  <a href=\"https://www.youtube.com/watch?v=utPRvqhXfoo\" title=\"Amazon gave Ring video to police without user’s permission (FOR ANY PURPOSE!)\" alt=\"Amazon gave Ring video to police without user’s permission (FOR ANY PURPOSE!)\"><img src=\"/image/yid-utPRvqhXfoo.jpg\" alt=\"Amazon gave Ring video to police without user’s permission (FOR ANY PURPOSE!)\" class=\"card-img\"></a>\n  <div class=\"card-body\">\n    <a href=\"https://www.youtube.com/watch?v=utPRvqhXfoo\" title=\"Amazon gave Ring video to police without user’s permission (FOR ANY PURPOSE!)\" class=\"btn btn-warning\">Play Video</a>\n  </div>\n</div>\n<div class=\"card card-section bg-dark text-warning shadow\">\n  <div class=\"card-header\">48 Dirty Little Secrets Cryptographers Don’t Want You To Know</div>\n  <a href=\"https://www.youtube.com/watch?v=iZa_XKpj9X4\" title=\"48 Dirty Little Secrets Cryptographers Don’t Want You To Know\" alt=\"48 Dirty Little Secrets Cryptographers Don’t Want You To Know\"><img src=\"/image/yid-iZa_XKpj9X4.jpg\" alt=\"48 Dirty Little Secrets Cryptographers Don’t Want You To Know\" class=\"card-img\"></a>\n  <div class=\"card-body\">\n    <a href=\"https://www.youtube.com/watch?v=iZa_XKpj9X4\" title=\"48 Dirty Little Secrets Cryptographers Don’t Want You To Know\" class=\"btn btn-warning\">Play Video</a>\n  </div>\n</div>\n<div class=\"card card-section bg-dark text-warning shadow\">\n  <div class=\"card-header\">Broadpwn: Remotely Compromising Android and iOS via a Bug in Broadcom&#x27;s Wi-Fi Chipsets</div>\n  <a href=\"https://www.youtube.com/watch?v=TDk2RId8LFo\" title=\"Broadpwn: Remotely Compromising Android and iOS via a Bug in Broadcom&#x27;s Wi-Fi Chipsets\" alt=\"Broadpwn: Remotely Compromising Android and iOS via a Bug in Broadcom&#x27;s Wi-Fi Chipsets\"><img src=\"/image/yid-TDk2RId8LFo.jpg\" alt=\"Broadpwn: Remotely Compromising Android and iOS via a Bug in Broadcom&#x27;s Wi-Fi Chipsets\" class=\"card-img\"></a>\n  <div class=\"card-body\">\n    <a href=\"https://www.youtube.com/watch?v=TDk2RId8LFo\" title=\"Broadpwn: Remotely Compromising Android and iOS via a Bug in Broadcom&#x27;s Wi-Fi Chipsets\" class=\"btn btn-warning\">Play Video</a>\n  </div>\n</div>\n<div class=\"card card-section bg-dark text-warning shadow\">\n  <div class=\"card-header\">Police are tracking you and your license plates</div>\n  <a href=\"https://www.youtube.com/watch?v=DH7edXaZS0A\" title=\"Police are tracking you and your license plates\" alt=\"Police are tracking you and your license plates\"><img src=\"/image/yid-DH7edXaZS0A.jpg\" alt=\"Police are tracking you and your license plates\" class=\"card-img\"></a>\n  <div class=\"card-body\">\n    <a href=\"https://www.youtube.com/watch?v=DH7edXaZS0A\" title=\"Police are tracking you and your license plates\" class=\"btn btn-warning\">Play Video</a>\n  </div>\n</div>\n<div class=\"card card-section bg-dark text-warning shadow\">\n  <div class=\"card-header\">The Stingray: How Law Enforcement Can Track Your Every Move</div>\n  <a href=\"https://www.youtube.com/watch?v=wzSgLpNrr2E\" title=\"The Stingray: How Law Enforcement Can Track Your Every Move\" alt=\"The Stingray: How Law Enforcement Can Track Your Every Move\"><img src=\"/image/yid-wzSgLpNrr2E.jpg\" alt=\"The Stingray: How Law Enforcement Can Track Your Every Move\" class=\"card-img\"></a>\n  <div class=\"card-body\">\n    <a href=\"https://www.youtube.com/watch?v=wzSgLpNrr2E\" title=\"The Stingray: How Law Enforcement Can Track Your Every Move\" class=\"btn btn-warning\">Play Video</a>\n  </div>\n</div>\n<div class=\"card card-section bg-dark text-warning shadow\">\n  <div class=\"card-header\">What Are My Rights With Police? (When I Get Pulled Over)</div>\n  <a href=\"https://www.youtube.com/watch?v=f26QJKREYB8&t=44\" title=\"What Are My Rights With Police? (When I Get Pulled Over)\" alt=\"What Are My Rights With Police? (When I Get Pulled Over)\"><img src=\"/image/yid-f26QJKREYB8.jpg\" alt=\"What Are My Rights With Police? (When I Get Pulled Over)\" class=\"card-img\"></a>\n  <div class=\"card-body\">\n    <a href=\"https://www.youtube.com/watch?v=f26QJKREYB8&t=44\" title=\"What Are My Rights With Police? (When I Get Pulled Over)\" class=\"btn btn-warning\">Play Video</a>\n  </div>\n</div>\n<div class=\"card card-section bg-dark text-warning shadow\">\n  <div class=\"card-header\">Michigan Police Sergeant Doesn&#x27;t Know The Law</div>\n  <a href=\"https://www.youtube.com/watch?v=6wsDmZo9UMI\" title=\"Michigan Police Sergeant Doesn&#x27;t Know The Law\" alt=\"Michigan Police Sergeant Doesn&#x27;t Know The Law\"><img src=\"/image/yid-6wsDmZo9UMI.jpg\" alt=\"Michigan Police Sergeant Doesn&#x27;t Know The Law\" class=\"card-img\"></a>\n  <div class=\"card-body\">\n    <a href=\"https://www.youtube.com/watch?v=6wsDmZo9UMI\" title=\"Michigan Police Sergeant Doesn&#x27;t Know The Law\" class=\"btn btn-warning\">Play Video</a>\n  </div>\n</div>\n<div class=\"card card-section bg-dark text-warning shadow\">\n  <div class=\"card-header\">Don&#x27;t Talk to the Police</div>\n  <a href=\"https://www.youtube.com/watch?v=d-7o9xYp7eE\" title=\"Don&#x27;t Talk to the Police\" alt=\"Don&#x27;t Talk to the Police\"><img src=\"/image/yid-d-7o9xYp7eE.jpg\" alt=\"Don&#x27;t Talk to the Police\" class=\"card-img\"></a>\n  <div class=\"card-body\">\n    <a href=\"https://www.youtube.com/watch?v=d-7o9xYp7eE\" title=\"Don&#x27;t Talk to the Police\" class=\"btn btn-warning\">Play Video</a>\n  </div>\n</div>\n<div class=\"card card-section bg-dark text-warning shadow\">\n  <div class=\"card-header\">How to make a simple $7 IMSI Catcher</div>\n  <a href=\"https://www.youtube.com/watch?v=UjwgNd_as30\" title=\"How to make a simple $7 IMSI Catcher\" alt=\"How to make a simple $7 IMSI Catcher\"><img src=\"/image/yid-UjwgNd_as30.jpg\" alt=\"How to make a simple $7 IMSI Catcher\" class=\"card-img\"></a>\n  <div class=\"card-body\">\n    <a href=\"https://www.youtube.com/watch?v=UjwgNd_as30\" title=\"How to make a simple $7 IMSI Catcher\" class=\"btn btn-warning\">Play Video</a>\n  </div>\n</div>\n<div class=\"card card-section bg-dark text-warning shadow\">\n  <div class=\"card-header\">Catching IMSI Catchers</div>\n  <a href=\"https://www.youtube.com/watch?v=eivHO1OzF5E\" title=\"Catching IMSI Catchers\" alt=\"Catching IMSI Catchers\"><img src=\"/image/yid-eivHO1OzF5E.jpg\" alt=\"Catching IMSI Catchers\" class=\"card-img\"></a>\n  <div class=\"card-body\">\n    <a href=\"https://www.youtube.com/watch?v=eivHO1OzF5E\" title=\"Catching IMSI Catchers\" class=\"btn btn-warning\">Play Video</a>\n  </div>\n</div>\n<div class=\"card card-section bg-dark text-warning shadow\">\n  <div class=\"card-header\">Project Overwatch: Multinational Effort to Combat IMSI Catchers (Intercept SMS And Track Location For $7)</div>\n  <a href=\"https://www.youtube.com/watch?v=UG5juhuhE2g\" title=\"Project Overwatch: Multinational Effort to Combat IMSI Catchers (Intercept SMS And Track Location For $7)\" alt=\"Project Overwatch: Multinational Effort to Combat IMSI Catchers (Intercept SMS And Track Location For $7)\"><img src=\"/image/yid-UG5juhuhE2g.jpg\" alt=\"Project Overwatch: Multinational Effort to Combat IMSI Catchers (Intercept SMS And Track Location For $7)\" class=\"card-img\"></a>\n  <div class=\"card-body\">\n    <a href=\"https://www.youtube.com/watch?v=UG5juhuhE2g\" title=\"Project Overwatch: Multinational Effort to Combat IMSI Catchers (Intercept SMS And Track Location For $7)\" class=\"btn btn-warning\">Play Video</a>\n  </div>\n</div>\n<div class=\"card card-section bg-dark text-warning shadow\">\n  <div class=\"card-header\">BSIDES CPT 2019 - Hacking satellites with Software Defined Radio (SDR) - Gerard de Jong</div>\n  <a href=\"https://www.youtube.com/watch?v=gMwciWchH3Q\" title=\"BSIDES CPT 2019 - Hacking satellites with Software Defined Radio (SDR) - Gerard de Jong\" alt=\"BSIDES CPT 2019 - Hacking satellites with Software Defined Radio (SDR) - Gerard de Jong\"><img src=\"/image/yid-gMwciWchH3Q.jpg\" alt=\"BSIDES CPT 2019 - Hacking satellites with Software Defined Radio (SDR) - Gerard de Jong\" class=\"card-img\"></a>\n  <div class=\"card-body\">\n    <a href=\"https://www.youtube.com/watch?v=gMwciWchH3Q\" title=\"BSIDES CPT 2019 - Hacking satellites with Software Defined Radio (SDR) - Gerard de Jong\" class=\"btn btn-warning\">Play Video</a>\n  </div>\n</div>\n<div class=\"card card-section bg-dark text-warning shadow\">\n  <div class=\"card-header\">The Coolest Radio You&#x27;ve Probably Never Heard Of</div>\n  <a href=\"https://www.youtube.com/watch?v=h4x7cGALaC8&t=61\" title=\"The Coolest Radio You&#x27;ve Probably Never Heard Of\" alt=\"The Coolest Radio You&#x27;ve Probably Never Heard Of\"><img src=\"/image/yid-h4x7cGALaC8.jpg\" alt=\"The Coolest Radio You&#x27;ve Probably Never Heard Of\" class=\"card-img\"></a>\n  <div class=\"card-body\">\n    <a href=\"https://www.youtube.com/watch?v=h4x7cGALaC8&t=61\" title=\"The Coolest Radio You&#x27;ve Probably Never Heard Of\" class=\"btn btn-warning\">Play Video</a>\n  </div>\n</div>\n<div class=\"card card-section bg-dark text-warning shadow\">\n  <div class=\"card-header\">Locating Cellular Signal with HackRF Spectrum Analyzer SDR Software</div>\n  <a href=\"https://www.youtube.com/watch?v=aFHWAEb3sn4\" title=\"Locating Cellular Signal with HackRF Spectrum Analyzer SDR Software\" alt=\"Locating Cellular Signal with HackRF Spectrum Analyzer SDR Software\"><img src=\"/image/yid-aFHWAEb3sn4.jpg\" alt=\"Locating Cellular Signal with HackRF Spectrum Analyzer SDR Software\" class=\"card-img\"></a>\n  <div class=\"card-body\">\n    <a href=\"https://www.youtube.com/watch?v=aFHWAEb3sn4\" title=\"Locating Cellular Signal with HackRF Spectrum Analyzer SDR Software\" class=\"btn btn-warning\">Play Video</a>\n  </div>\n</div>\n<div class=\"card card-section bg-dark text-warning shadow\">\n  <div class=\"card-header\">How Telephone Phreaking Worked (Starts at 4:30)</div>\n  <a href=\"https://www.youtube.com/watch?v=4tHyZdtXULw\" title=\"How Telephone Phreaking Worked (Starts at 4:30)\" alt=\"How Telephone Phreaking Worked (Starts at 4:30)\"><img src=\"/image/yid-4tHyZdtXULw.jpg\" alt=\"How Telephone Phreaking Worked (Starts at 4:30)\" class=\"card-img\"></a>\n  <div class=\"card-body\">\n    <a href=\"https://www.youtube.com/watch?v=4tHyZdtXULw\" title=\"How Telephone Phreaking Worked (Starts at 4:30)\" class=\"btn btn-warning\">Play Video</a>\n  </div>\n</div>\n<div class=\"card card-section bg-dark text-warning shadow\">\n  <div class=\"card-header\">Hackers The History Of Hacking - Phone Phreaking, Cap.Crunch, Wozniak, Mitnick</div>\n  <a href=\"https://www.youtube.com/watch?v=FufYSx2_6Bg\" title=\"Hackers The History Of Hacking - Phone Phreaking, Cap.Crunch, Wozniak, Mitnick\" alt=\"Hackers The History Of Hacking - Phone Phreaking, Cap.Crunch, Wozniak, Mitnick\"><img src=\"/image/yid-FufYSx2_6Bg.jpg\" alt=\"Hackers The History Of Hacking - Phone Phreaking, Cap.Crunch, Wozniak, Mitnick\" class=\"card-img\"></a>\n  <div class=\"card-body\">\n    <a href=\"https://www.youtube.com/watch?v=FufYSx2_6Bg\" title=\"Hackers The History Of Hacking - Phone Phreaking, Cap.Crunch, Wozniak, Mitnick\" class=\"btn btn-warning\">Play Video</a>\n  </div>\n</div>\n<div class=\"card card-section bg-dark text-warning shadow\">\n  <div class=\"card-header\">Dutch Hacker Attacking Pentagon via FTP (1991)</div>\n  <a href=\"https://www.youtube.com/watch?v=3ZU2DHcjrcI\" title=\"Dutch Hacker Attacking Pentagon via FTP (1991)\" alt=\"Dutch Hacker Attacking Pentagon via FTP (1991)\"><img src=\"/image/yid-3ZU2DHcjrcI.jpg\" alt=\"Dutch Hacker Attacking Pentagon via FTP (1991)\" class=\"card-img\"></a>\n  <div class=\"card-body\">\n    <a href=\"https://www.youtube.com/watch?v=3ZU2DHcjrcI\" title=\"Dutch Hacker Attacking Pentagon via FTP (1991)\" class=\"btn btn-warning\">Play Video</a>\n  </div>\n</div>\n<div class=\"card card-section bg-dark text-warning shadow\">\n  <div class=\"card-header\">The Jerky Boys - Piano Tuner</div>\n  <a href=\"https://www.youtube.com/watch?v=eajkTddpeQQ\" title=\"The Jerky Boys - Piano Tuner\" alt=\"The Jerky Boys - Piano Tuner\"><img src=\"/image/yid-eajkTddpeQQ.jpg\" alt=\"The Jerky Boys - Piano Tuner\" class=\"card-img\"></a>\n  <div class=\"card-body\">\n    <a href=\"https://www.youtube.com/watch?v=eajkTddpeQQ\" title=\"The Jerky Boys - Piano Tuner\" class=\"btn btn-warning\">Play Video</a>\n  </div>\n</div>\n<div class=\"card card-section bg-dark text-warning shadow\">\n  <div class=\"card-header\">Jerky Boys - Sol Rosenberg&#x27;s Glasses</div>\n  <a href=\"https://www.youtube.com/watch?v=jF0ajgT_09s\" title=\"Jerky Boys - Sol Rosenberg&#x27;s Glasses\" alt=\"Jerky Boys - Sol Rosenberg&#x27;s Glasses\"><img src=\"/image/yid-jF0ajgT_09s.jpg\" alt=\"Jerky Boys - Sol Rosenberg&#x27;s Glasses\" class=\"card-img\"></a>\n  <div class=\"card-body\">\n    <a href=\"https://www.youtube.com/watch?v=jF0ajgT_09s\" title=\"Jerky Boys - Sol Rosenberg&#x27;s Glasses\" class=\"btn btn-warning\">Play Video</a>\n  </div>\n</div>\n<div class=\"card card-section bg-dark text-warning shadow\">\n  <div class=\"card-header\">The Jerky Boys - Drinking Problem</div>\n  <a href=\"https://www.youtube.com/watch?v=ZllDjMXSjOE\" title=\"The Jerky Boys - Drinking Problem\" alt=\"The Jerky Boys - Drinking Problem\"><img src=\"/image/yid-ZllDjMXSjOE.jpg\" alt=\"The Jerky Boys - Drinking Problem\" class=\"card-img\"></a>\n  <div class=\"card-body\">\n    <a href=\"https://www.youtube.com/watch?v=ZllDjMXSjOE\" title=\"The Jerky Boys - Drinking Problem\" class=\"btn btn-warning\">Play Video</a>\n  </div>\n</div>\n<div class=\"card card-section bg-dark text-warning shadow\">\n  <div class=\"card-header\">Cact-Eye Hidden Camera Prank Calls</div>\n  <a href=\"https://www.youtube.com/watch?v=p1kWQOa-ULM\" title=\"Cact-Eye Hidden Camera Prank Calls\" alt=\"Cact-Eye Hidden Camera Prank Calls\"><img src=\"/image/yid-p1kWQOa-ULM.jpg\" alt=\"Cact-Eye Hidden Camera Prank Calls\" class=\"card-img\"></a>\n  <div class=\"card-body\">\n    <a href=\"https://www.youtube.com/watch?v=p1kWQOa-ULM\" title=\"Cact-Eye Hidden Camera Prank Calls\" class=\"btn btn-warning\">Play Video</a>\n  </div>\n</div>\n<div class=\"card card-section bg-dark text-warning shadow\">\n  <div class=\"card-header\">Radio and Swap Shop Prank Calls</div>\n  <a href=\"https://www.youtube.com/watch?v=kHA79JHGlOk\" title=\"Radio and Swap Shop Prank Calls\" alt=\"Radio and Swap Shop Prank Calls\"><img src=\"/image/yid-kHA79JHGlOk.jpg\" alt=\"Radio and Swap Shop Prank Calls\" class=\"card-img\"></a>\n  <div class=\"card-body\">\n    <a href=\"https://www.youtube.com/watch?v=kHA79JHGlOk\" title=\"Radio and Swap Shop Prank Calls\" class=\"btn btn-warning\">Play Video</a>\n  </div>\n</div>\n<div class=\"card card-section bg-dark text-warning shadow\">\n  <div class=\"card-header\">Tour of the Cacti Radio Studio</div>\n  <a href=\"https://www.youtube.com/watch?v=Q1YBk6tbM8s\" title=\"Tour of the Cacti Radio Studio\" alt=\"Tour of the Cacti Radio Studio\"><img src=\"/image/yid-Q1YBk6tbM8s.jpg\" alt=\"Tour of the Cacti Radio Studio\" class=\"card-img\"></a>\n  <div class=\"card-body\">\n    <a href=\"https://www.youtube.com/watch?v=Q1YBk6tbM8s\" title=\"Tour of the Cacti Radio Studio\" class=\"btn btn-warning\">Play Video</a>\n  </div>\n</div>\n<div class=\"card card-section bg-dark text-warning shadow\">\n  <div class=\"card-header\">Pump Up The Volume</div>\n  <a href=\"https://www.youtube.com/watch?v=uo-km-qfJe8\" title=\"Pump Up The Volume\" alt=\"Pump Up The Volume\"><img src=\"/image/yid-uo-km-qfJe8.jpg\" alt=\"Pump Up The Volume\" class=\"card-img\"></a>\n  <div class=\"card-body\">\n    <a href=\"https://www.youtube.com/watch?v=uo-km-qfJe8\" title=\"Pump Up The Volume\" class=\"btn btn-warning\">Play Video</a>\n  </div>\n</div>\n<div class=\"card card-section bg-dark text-warning shadow\">\n  <div class=\"card-header\">Classroom Craziness Compilation</div>\n  <a href=\"https://www.youtube.com/watch?v=lwEFEIxcj4Q\" title=\"Classroom Craziness Compilation\" alt=\"Classroom Craziness Compilation\"><img src=\"/image/yid-lwEFEIxcj4Q.jpg\" alt=\"Classroom Craziness Compilation\" class=\"card-img\"></a>\n  <div class=\"card-body\">\n    <a href=\"https://www.youtube.com/watch?v=lwEFEIxcj4Q\" title=\"Classroom Craziness Compilation\" class=\"btn btn-warning\">Play Video</a>\n  </div>\n</div>\n<div class=\"card card-section bg-dark text-warning shadow\">\n  <div class=\"card-header\">*Trance* Orbital - Halcyon and On and On ( Hackers / 1995 )</div>\n  <a href=\"https://www.youtube.com/watch?v=33WuGp6fs3s\" title=\"*Trance* Orbital - Halcyon and On and On ( Hackers / 1995 )\" alt=\"*Trance* Orbital - Halcyon and On and On ( Hackers / 1995 )\"><img src=\"/image/yid-33WuGp6fs3s.jpg\" alt=\"*Trance* Orbital - Halcyon and On and On ( Hackers / 1995 )\" class=\"card-img\"></a>\n  <div class=\"card-body\">\n    <a href=\"https://www.youtube.com/watch?v=33WuGp6fs3s\" title=\"*Trance* Orbital - Halcyon and On and On ( Hackers / 1995 )\" class=\"btn btn-warning\">Play Video</a>\n  </div>\n</div>\n<div class=\"card card-section bg-dark text-warning shadow\">\n  <div class=\"card-header\">The Conscience of a Hacker</div>\n  <a href=\"https://www.youtube.com/watch?v=0tEnnvZbYek\" title=\"The Conscience of a Hacker\" alt=\"The Conscience of a Hacker\"><img src=\"/image/yid-0tEnnvZbYek.jpg\" alt=\"The Conscience of a Hacker\" class=\"card-img\"></a>\n  <div class=\"card-body\">\n    <a href=\"https://www.youtube.com/watch?v=0tEnnvZbYek\" title=\"The Conscience of a Hacker\" class=\"btn btn-warning\">Play Video</a>\n  </div>\n</div>",
  "text": "Steve Jobs Interview about the Blue Box Story[1]\nBlue Box | Homemade Replica Blue Box For Phone Phreaking[2]\n20th Anniversary Redbox Radioshack tone dialer EC-389 Catalog no 65-721[3]\nOldschool Radioshack Redbox pocket tone dialer[4]\nEmmanuel Goldstein, sock puppet Q&A[5]\nPhiber Optik - Last Interview Before 1 Year In Prison (1993)[6]\nJoybubbles ❤️[7]\nCovid Crops Prank Call[8]\nHarassing Black Friday Wal-Mart Customers with Prank Calls[9]\nThe Last HOPE (2008) - The Art of Social Engineering[10]\nPhone Phreak Captain Crunch Rare Interview from '78[11]\n2600 Interview with Kevin Mitnick[12]\nL0pht Heavy Industries[13]\nAmazon gave Ring video to police without user’s permission (FOR ANY PURPOSE!)[14]\n48 Dirty Little Secrets Cryptographers Don’t Want You To Know[15]\nBroadpwn: Remotely Compromising Android and iOS via a Bug in Broadcom's Wi-Fi Chipsets[16]\nPolice are tracking you and your license plates[17]\nThe Stingray: How Law Enforcement Can Track Your Every Move[18]\nWhat Are My Rights With Police? (When I Get Pulled Over)[19]\nMichigan Police Sergeant Doesn't Know The Law[20]\nDon't Talk to the Police[21]\nHow to make a simple $7 IMSI Catcher[22]\nCatching IMSI Catchers[23]\nProject Overwatch: Multinational Effort to Combat IMSI Catchers (Intercept SMS And Track Location For $7)[24]\nBSIDES CPT 2019 - Hacking satellites with Software Defined Radio (SDR) - Gerard de Jong[25]\nThe Coolest Radio You've Probably Never Heard Of[26]\nLocating Cellular Signal with HackRF Spectrum Analyzer SDR Software[27]\nHow Telephone Phreaking Worked (Starts at 4:30)[28]\nHackers The History Of Hacking - Phone Phreaking, Cap.Crunch, Wozniak, Mitnick[29]\nDutch Hacker Attacking Pentagon via FTP (1991)[30]\nThe Jerky Boys - Piano Tuner[31]\nJerky Boys - Sol Rosenberg's Glasses[32]\nThe Jerky Boys - Drinking Problem[33]\nCact-Eye Hidden Camera Prank Calls[34]\nRadio and Swap Shop Prank Calls[35]\nTour of the Cacti Radio Studio[36]\nPump Up The Volume[37]\nClassroom Craziness Compilation[38]\n*Trance* Orbital - Halcyon and On and On ( Hackers / 1995 )[39]\nThe Conscience of a Hacker[40]\n \nReferences\n[1]: https://www.youtube.com/watch?v=HFURM8O-oYI&t=13\n[2]: https://www.youtube.com/watch?v=CRp8XvwNSD0\n[3]: https://www.youtube.com/watch?v=JAj0BMIODWo\n[4]: https://www.youtube.com/watch?v=AXZMgHKhefk\n[5]: https://www.youtube.com/watch?v=AJir12xkUY4\n[6]: https://www.youtube.com/watch?v=hkQ0BOrFTJk\n[7]: https://www.youtube.com/watch?v=vVZm7I1CTBs\n[8]: https://www.youtube.com/watch?v=jG1T34uE58o\n[9]: https://www.youtube.com/watch?v=RGmdwiz9zDE\n[10]: https://www.youtube.com/watch?v=1M9pwYQSbQU\n[11]: https://www.youtube.com/watch?v=n6TjjE8NHV0\n[12]: https://www.youtube.com/watch?v=6OJyaML7_rw\n[13]: https://www.youtube.com/watch?v=VVJldn_MmMY\n[14]: https://www.youtube.com/watch?v=utPRvqhXfoo\n[15]: https://www.youtube.com/watch?v=iZa_XKpj9X4\n[16]: https://www.youtube.com/watch?v=TDk2RId8LFo\n[17]: https://www.youtube.com/watch?v=DH7edXaZS0A\n[18]: https://www.youtube.com/watch?v=wzSgLpNrr2E\n[19]: https://www.youtube.com/watch?v=f26QJKREYB8&t=44\n[20]: https://www.youtube.com/watch?v=6wsDmZo9UMI\n[21]: https://www.youtube.com/watch?v=d-7o9xYp7eE\n[22]: https://www.youtube.com/watch?v=UjwgNd_as30\n[23]: https://www.youtube.com/watch?v=eivHO1OzF5E\n[24]: https://www.youtube.com/watch?v=UG5juhuhE2g\n[25]: https://www.youtube.com/watch?v=gMwciWchH3Q\n[26]: https://www.youtube.com/watch?v=h4x7cGALaC8&t=61\n[27]: https://www.youtube.com/watch?v=aFHWAEb3sn4\n[28]: https://www.youtube.com/watch?v=4tHyZdtXULw\n[29]: https://www.youtube.com/watch?v=FufYSx2_6Bg\n[30]: https://www.youtube.com/watch?v=3ZU2DHcjrcI\n[31]: https://www.youtube.com/watch?v=eajkTddpeQQ\n[32]: https://www.youtube.com/watch?v=jF0ajgT_09s\n[33]: https://www.youtube.com/watch?v=ZllDjMXSjOE\n[34]: https://www.youtube.com/watch?v=p1kWQOa-ULM\n[35]: https://www.youtube.com/watch?v=kHA79JHGlOk\n[36]: https://www.youtube.com/watch?v=Q1YBk6tbM8s\n[37]: https://www.youtube.com/watch?v=uo-km-qfJe8\n[38]: https://www.youtube.com/watch?v=lwEFEIxcj4Q\n[39]: https://www.youtube.com/watch?v=33WuGp6fs3s\n[40]: https://www.youtube.com/watch?v=0tEnnvZbYek",
  "images": [
    {
      "title": "Steve Jobs Interview about the Blue Box Story",
      "url": "yid-HFURM8O-oYI.jpg"
    },
    {
      "title": "Blue Box | Homemade Replica Blue Box For Phone Phreaking",
      "url": "yid-CRp8XvwNSD0.jpg"
    },
    {
      "title": "20th Anniversary Redbox Radioshack tone dialer EC-389 Catalog no 65-721",
      "url": "yid-JAj0BMIODWo.jpg"
    },
    {
      "title": "Oldschool Radioshack Redbox pocket tone dialer",
      "url": "yid-AXZMgHKhefk.jpg"
    },
    {
      "title": "Emmanuel Goldstein, sock puppet Q&A",
      "url": "yid-AJir12xkUY4.jpg"
    },
    {
      "title": "Phiber Optik - Last Interview Before 1 Year In Prison (1993)",
      "url": "yid-hkQ0BOrFTJk.jpg"
    },
    {
      "title": "Joybubbles ❤️",
      "url": "yid-vVZm7I1CTBs.jpg"
    },
    {
      "title": "Covid Crops Prank Call",
      "url": "yid-jG1T34uE58o.jpg"
    },
    {
      "title": "Harassing Black Friday Wal-Mart Customers with Prank Calls",
      "url": "yid-RGmdwiz9zDE.jpg"
    },
    {
      "title": "The Last HOPE (2008) - The Art of Social Engineering",
      "url": "yid-1M9pwYQSbQU.jpg"
    },
    {
      "title": "Phone Phreak Captain Crunch Rare Interview from '78",
      "url": "yid-n6TjjE8NHV0.jpg"
    },
    {
      "title": "2600 Interview with Kevin Mitnick",
      "url": "yid-6OJyaML7_rw.jpg"
    },
    {
      "title": "L0pht Heavy Industries",
      "url": "yid-VVJldn_MmMY.jpg"
    },
    {
      "title": "Amazon gave Ring video to police without user’s permission (FOR ANY PURPOSE!)",
      "url": "yid-utPRvqhXfoo.jpg"
    },
    {
      "title": "48 Dirty Little Secrets Cryptographers Don’t Want You To Know",
      "url": "yid-iZa_XKpj9X4.jpg"
    },
    {
      "title": "Broadpwn: Remotely Compromising Android and iOS via a Bug in Broadcom's Wi-Fi Chipsets",
      "url": "yid-TDk2RId8LFo.jpg"
    },
    {
      "title": "Police are tracking you and your license plates",
      "url": "yid-DH7edXaZS0A.jpg"
    },
    {
      "title": "The Stingray: How Law Enforcement Can Track Your Every Move",
      "url": "yid-wzSgLpNrr2E.jpg"
    },
    {
      "title": "What Are My Rights With Police? (When I Get Pulled Over)",
      "url": "yid-f26QJKREYB8.jpg"
    },
    {
      "title": "Michigan Police Sergeant Doesn't Know The Law",
      "url": "yid-6wsDmZo9UMI.jpg"
    },
    {
      "title": "Don't Talk to the Police",
      "url": "yid-d-7o9xYp7eE.jpg"
    },
    {
      "title": "How to make a simple $7 IMSI Catcher",
      "url": "yid-UjwgNd_as30.jpg"
    },
    {
      "title": "Catching IMSI Catchers",
      "url": "yid-eivHO1OzF5E.jpg"
    },
    {
      "title": "Project Overwatch: Multinational Effort to Combat IMSI Catchers (Intercept SMS And Track Location For $7)",
      "url": "yid-UG5juhuhE2g.jpg"
    },
    {
      "title": "BSIDES CPT 2019 - Hacking satellites with Software Defined Radio (SDR) - Gerard de Jong",
      "url": "yid-gMwciWchH3Q.jpg"
    },
    {
      "title": "The Coolest Radio You've Probably Never Heard Of",
      "url": "yid-h4x7cGALaC8.jpg"
    },
    {
      "title": "Locating Cellular Signal with HackRF Spectrum Analyzer SDR Software",
      "url": "yid-aFHWAEb3sn4.jpg"
    },
    {
      "title": "How Telephone Phreaking Worked (Starts at 4:30)",
      "url": "yid-4tHyZdtXULw.jpg"
    },
    {
      "title": "Hackers The History Of Hacking - Phone Phreaking, Cap.Crunch, Wozniak, Mitnick",
      "url": "yid-FufYSx2_6Bg.jpg"
    },
    {
      "title": "Dutch Hacker Attacking Pentagon via FTP (1991)",
      "url": "yid-3ZU2DHcjrcI.jpg"
    },
    {
      "title": "The Jerky Boys - Piano Tuner",
      "url": "yid-eajkTddpeQQ.jpg"
    },
    {
      "title": "Jerky Boys - Sol Rosenberg's Glasses",
      "url": "yid-jF0ajgT_09s.jpg"
    },
    {
      "title": "The Jerky Boys - Drinking Problem",
      "url": "yid-ZllDjMXSjOE.jpg"
    },
    {
      "title": "Cact-Eye Hidden Camera Prank Calls",
      "url": "yid-p1kWQOa-ULM.jpg"
    },
    {
      "title": "Radio and Swap Shop Prank Calls",
      "url": "yid-kHA79JHGlOk.jpg"
    },
    {
      "title": "Tour of the Cacti Radio Studio",
      "url": "yid-Q1YBk6tbM8s.jpg"
    },
    {
      "title": "Pump Up The Volume",
      "url": "yid-uo-km-qfJe8.jpg"
    },
    {
      "title": "Classroom Craziness Compilation",
      "url": "yid-lwEFEIxcj4Q.jpg"
    },
    {
      "title": "*Trance* Orbital - Halcyon and On and On ( Hackers / 1995 )",
      "url": "yid-33WuGp6fs3s.jpg"
    },
    {
      "title": "The Conscience of a Hacker",
      "url": "yid-0tEnnvZbYek.jpg"
    }
  ],
  "links": [
    {
      "title": "Steve Jobs Interview about the Blue Box Story",
      "url": "https://www.youtube.com/watch?v=HFURM8O-oYI&t=13",
      "hostname": "www.youtube.com"
    },
    {
      "title": "Blue Box | Homemade Replica Blue Box For Phone Phreaking",
      "url": "https://www.youtube.com/watch?v=CRp8XvwNSD0",
      "hostname": "www.youtube.com"
    },
    {
      "title": "20th Anniversary Redbox Radioshack tone dialer EC-389 Catalog no 65-721",
      "url": "https://www.youtube.com/watch?v=JAj0BMIODWo",
      "hostname": "www.youtube.com"
    },
    {
      "title": "Oldschool Radioshack Redbox pocket tone dialer",
      "url": "https://www.youtube.com/watch?v=AXZMgHKhefk",
      "hostname": "www.youtube.com"
    },
    {
      "title": "Emmanuel Goldstein, sock puppet Q&A",
      "url": "https://www.youtube.com/watch?v=AJir12xkUY4",
      "hostname": "www.youtube.com"
    },
    {
      "title": "Phiber Optik - Last Interview Before 1 Year In Prison (1993)",
      "url": "https://www.youtube.com/watch?v=hkQ0BOrFTJk",
      "hostname": "www.youtube.com"
    },
    {
      "title": "Joybubbles ❤️",
      "url": "https://www.youtube.com/watch?v=vVZm7I1CTBs",
      "hostname": "www.youtube.com"
    },
    {
      "title": "Covid Crops Prank Call",
      "url": "https://www.youtube.com/watch?v=jG1T34uE58o",
      "hostname": "www.youtube.com"
    },
    {
      "title": "Harassing Black Friday Wal-Mart Customers with Prank Calls",
      "url": "https://www.youtube.com/watch?v=RGmdwiz9zDE",
      "hostname": "www.youtube.com"
    },
    {
      "title": "The Last HOPE (2008) - The Art of Social Engineering",
      "url": "https://www.youtube.com/watch?v=1M9pwYQSbQU",
      "hostname": "www.youtube.com"
    },
    {
      "title": "Phone Phreak Captain Crunch Rare Interview from '78",
      "url": "https://www.youtube.com/watch?v=n6TjjE8NHV0",
      "hostname": "www.youtube.com"
    },
    {
      "title": "2600 Interview with Kevin Mitnick",
      "url": "https://www.youtube.com/watch?v=6OJyaML7_rw",
      "hostname": "www.youtube.com"
    },
    {
      "title": "L0pht Heavy Industries",
      "url": "https://www.youtube.com/watch?v=VVJldn_MmMY",
      "hostname": "www.youtube.com"
    },
    {
      "title": "Amazon gave Ring video to police without user’s permission (FOR ANY PURPOSE!)",
      "url": "https://www.youtube.com/watch?v=utPRvqhXfoo",
      "hostname": "www.youtube.com"
    },
    {
      "title": "48 Dirty Little Secrets Cryptographers Don’t Want You To Know",
      "url": "https://www.youtube.com/watch?v=iZa_XKpj9X4",
      "hostname": "www.youtube.com"
    },
    {
      "title": "Broadpwn: Remotely Compromising Android and iOS via a Bug in Broadcom's Wi-Fi Chipsets",
      "url": "https://www.youtube.com/watch?v=TDk2RId8LFo",
      "hostname": "www.youtube.com"
    },
    {
      "title": "Police are tracking you and your license plates",
      "url": "https://www.youtube.com/watch?v=DH7edXaZS0A",
      "hostname": "www.youtube.com"
    },
    {
      "title": "The Stingray: How Law Enforcement Can Track Your Every Move",
      "url": "https://www.youtube.com/watch?v=wzSgLpNrr2E",
      "hostname": "www.youtube.com"
    },
    {
      "title": "What Are My Rights With Police? (When I Get Pulled Over)",
      "url": "https://www.youtube.com/watch?v=f26QJKREYB8&t=44",
      "hostname": "www.youtube.com"
    },
    {
      "title": "Michigan Police Sergeant Doesn't Know The Law",
      "url": "https://www.youtube.com/watch?v=6wsDmZo9UMI",
      "hostname": "www.youtube.com"
    },
    {
      "title": "Don't Talk to the Police",
      "url": "https://www.youtube.com/watch?v=d-7o9xYp7eE",
      "hostname": "www.youtube.com"
    },
    {
      "title": "How to make a simple $7 IMSI Catcher",
      "url": "https://www.youtube.com/watch?v=UjwgNd_as30",
      "hostname": "www.youtube.com"
    },
    {
      "title": "Catching IMSI Catchers",
      "url": "https://www.youtube.com/watch?v=eivHO1OzF5E",
      "hostname": "www.youtube.com"
    },
    {
      "title": "Project Overwatch: Multinational Effort to Combat IMSI Catchers (Intercept SMS And Track Location For $7)",
      "url": "https://www.youtube.com/watch?v=UG5juhuhE2g",
      "hostname": "www.youtube.com"
    },
    {
      "title": "BSIDES CPT 2019 - Hacking satellites with Software Defined Radio (SDR) - Gerard de Jong",
      "url": "https://www.youtube.com/watch?v=gMwciWchH3Q",
      "hostname": "www.youtube.com"
    },
    {
      "title": "The Coolest Radio You've Probably Never Heard Of",
      "url": "https://www.youtube.com/watch?v=h4x7cGALaC8&t=61",
      "hostname": "www.youtube.com"
    },
    {
      "title": "Locating Cellular Signal with HackRF Spectrum Analyzer SDR Software",
      "url": "https://www.youtube.com/watch?v=aFHWAEb3sn4",
      "hostname": "www.youtube.com"
    },
    {
      "title": "How Telephone Phreaking Worked (Starts at 4:30)",
      "url": "https://www.youtube.com/watch?v=4tHyZdtXULw",
      "hostname": "www.youtube.com"
    },
    {
      "title": "Hackers The History Of Hacking - Phone Phreaking, Cap.Crunch, Wozniak, Mitnick",
      "url": "https://www.youtube.com/watch?v=FufYSx2_6Bg",
      "hostname": "www.youtube.com"
    },
    {
      "title": "Dutch Hacker Attacking Pentagon via FTP (1991)",
      "url": "https://www.youtube.com/watch?v=3ZU2DHcjrcI",
      "hostname": "www.youtube.com"
    },
    {
      "title": "The Jerky Boys - Piano Tuner",
      "url": "https://www.youtube.com/watch?v=eajkTddpeQQ",
      "hostname": "www.youtube.com"
    },
    {
      "title": "Jerky Boys - Sol Rosenberg's Glasses",
      "url": "https://www.youtube.com/watch?v=jF0ajgT_09s",
      "hostname": "www.youtube.com"
    },
    {
      "title": "The Jerky Boys - Drinking Problem",
      "url": "https://www.youtube.com/watch?v=ZllDjMXSjOE",
      "hostname": "www.youtube.com"
    },
    {
      "title": "Cact-Eye Hidden Camera Prank Calls",
      "url": "https://www.youtube.com/watch?v=p1kWQOa-ULM",
      "hostname": "www.youtube.com"
    },
    {
      "title": "Radio and Swap Shop Prank Calls",
      "url": "https://www.youtube.com/watch?v=kHA79JHGlOk",
      "hostname": "www.youtube.com"
    },
    {
      "title": "Tour of the Cacti Radio Studio",
      "url": "https://www.youtube.com/watch?v=Q1YBk6tbM8s",
      "hostname": "www.youtube.com"
    },
    {
      "title": "Pump Up The Volume",
      "url": "https://www.youtube.com/watch?v=uo-km-qfJe8",
      "hostname": "www.youtube.com"
    },
    {
      "title": "Classroom Craziness Compilation",
      "url": "https://www.youtube.com/watch?v=lwEFEIxcj4Q",
      "hostname": "www.youtube.com"
    },
    {
      "title": "*Trance* Orbital - Halcyon and On and On ( Hackers / 1995 )",
      "url": "https://www.youtube.com/watch?v=33WuGp6fs3s",
      "hostname": "www.youtube.com"
    },
    {
      "title": "The Conscience of a Hacker",
      "url": "https://www.youtube.com/watch?v=0tEnnvZbYek",
      "hostname": "www.youtube.com"
    }
  ]
}