{
  "name": "westland-warrior-the-dj",
  "id": "westland-warrior-the-dj",
  "title": "The Dj",
  "date": "2019-11-13T03:40:27.640Z",
  "image": "warrior-the-dj-cover.jpg",
  "attachments": {},
  "guid": "746302e0-9c34-4dbf-a8b0-b09bce9785d3",
  "md": "How To DJ For Beginners | Alison Wonderland\n-------------------------------------------\n\n[![](/image/yid-rzg8OPPKVdM.jpg)](https://www.youtube.com/watch?v=rzg8OPPKVdM)\n\nMariana BO\n----------\n\n[YouTube Channel](https://www.youtube.com/channel/UCXBxS3vJZmrKUTOmjG0XnKQ) / [YouTube Topic](https://www.youtube.com/channel/UC7orAmV1JD-j-cIxOW7gi3w)\n\nMariana BO (Tomorrowland Belgium 2019)\n--------------------------------------\n\n[![](/image/yid-dQRARRAhRLc.jpg)](https://www.youtube.com/watch?v=dQRARRAhRLc)\n\nMariana BO: Shankara\n--------------------\n\n[![](/image/yid-V7-JQcNm8W0.jpg)](https://www.youtube.com/watch?v=V7-JQcNm8W0)\n\nMATTN\n-----\n\n[YouTube Topic](https://www.youtube.com/channel/UCojmPu73tS_5hcxUOoCtHjw)\n\nMATTN (Tomorrowland Mainstage 2019)\n-----------------------------------\n\n[![](/image/yid-ksqBDYwqkHA.jpg)](https://www.youtube.com/watch?v=ksqBDYwqkHA)\n\nMATTN: Jungle Fever\n-------------------\n\n[![](/image/yid-F18eozyUKoM.jpg)](https://www.youtube.com/watch?v=F18eozyUKoM)\n\nPeggy Gou\n---------\n\n[YouTube Topic](https://www.youtube.com/channel/UConl7T_sh6sQCwYe8WrQNbQ)\n\nPeggy Gou (Palais des Beaux-Arts de Lille for Cercle)\n-----------------------------------------------------\n\n[![](/image/yid--UOMvxh4MYU.jpg)](https://www.youtube.com/watch?v=-UOMvxh4MYU)\n\nPeggy Gou: Starry Night\n-----------------------\n\n[![](/image/yid-r_wwmmo6UGY.jpg)](https://www.youtube.com/watch?v=r_wwmmo6UGY)\n\nMiss K8\n-------\n\n[YouTube Channel](https://www.youtube.com/channel/UC9QwEZj-KBlYzW3hbsgwS-Q)\n\nMiss K8 (Qlimax 2019)\n---------------------\n\n[![](/image/yid-Z0N1i7LwXXE.jpg)](https://www.youtube.com/watch?v=Z0N1i7LwXXE)\n\nMiss K8: Out Of The Frame\n-------------------------\n\n[![](/image/yid-k9sC2RcFsQg.jpg)](https://www.youtube.com/watch?v=k9sC2RcFsQg)\n\nCharlotte de Witte\n------------------\n\n[YouTube Channel](https://www.youtube.com/channel/UC-yOW3e6zBSo1JwLXq46Suw)\n\nCharlotte de Witte (Dour Festival 2017)\n---------------------------------------\n\n[![](/image/yid-AtZxg-OC5ho.jpg)](https://www.youtube.com/watch?v=AtZxg-OC5ho)\n\nCharlotte de Witte: Time\n------------------------\n\n[![](/image/yid-qNWQ5TGujVI.jpg)](https://www.youtube.com/watch?v=qNWQ5TGujVI)\n\nNERVO\n-----\n\n[YouTube Channel](https://www.youtube.com/channel/UCPIq_wSB6DYBtoee4KqSZnw)\n\nNERVO (Tomorrowland July 22, 2017)\n----------------------------------\n\n[![](/image/yid-_m9OgQkdVqQ.jpg)](https://www.youtube.com/watch?v=_m9OgQkdVqQ)\n\nNERVO: The Way We See The World\n-------------------------------\n\n[![](/image/yid-rTOMpaOd31g.jpg)](https://www.youtube.com/watch?v=rTOMpaOd31g)\n\nAlison Wonderland\n-----------------\n\n[YouTube Channel](https://www.youtube.com/channel/UCB6R4ceqzkFiNX6FjDNzuKw)\n\nAlison Wonderland (The Lab LA)\n------------------------------\n\n[![](/image/yid-HIXwkduDI3w.jpg)](https://www.youtube.com/watch?v=HIXwkduDI3w)\n\nAlison Wonderland: Peace\n------------------------\n\n[![](/image/yid-KbGV1KEXds4.jpg)](https://www.youtube.com/watch?v=KbGV1KEXds4)\n\nNina Kraviz\n-----------\n\n[YouTube Topic](https://www.youtube.com/channel/UCF6lav85ybIK3Umon9oI-dw)\n\nNina Kraviz (Tour Eiffel for Cercle)\n------------------------------------\n\n[![](/image/yid-oFvqo1dil7M.jpg)](https://www.youtube.com/watch?v=oFvqo1dil7M)\n\nNina Kraviz: Dream Machine\n--------------------------\n\n[![](/image/yid-JDJRg8sowP4.jpg)](https://www.youtube.com/watch?v=JDJRg8sowP4)",
  "html": "<div class=\"section yt\">\n  <header>\n    <h2>How To DJ For Beginners | Alison Wonderland</h2>\n  </header>\n  <figure>\n    <a href=\"https://www.youtube.com/watch?v=rzg8OPPKVdM\" class=\"no-tufte-underline\" title=\"How To DJ For Beginners | Alison Wonderland\">\n      <img src=\"/image/yid-rzg8OPPKVdM.jpg\" alt=\"How To DJ For Beginners | Alison Wonderland\">\n    </a>\n    <figcaption>How To DJ For Beginners | Alison Wonderland</figcaption>\n  </figure>\n  <p><a href=\"https://www.youtube.com/watch?v=rzg8OPPKVdM\" title=\"How To DJ For Beginners | Alison Wonderland\">Play Video</a></p>\n</div>\n<div class=\"section\">\n  <header>\n    <h2>Mariana BO</h2>\n  </header>\n  <p><a href=\"https://www.youtube.com/channel/UCXBxS3vJZmrKUTOmjG0XnKQ\">YouTube Channel</a> / <a href=\"https://www.youtube.com/channel/UC7orAmV1JD-j-cIxOW7gi3w\">YouTube Topic</a></p>\n</div>\n<div class=\"section yt\">\n  <header>\n    <h2>Mariana BO (Tomorrowland Belgium 2019)</h2>\n  </header>\n  <figure>\n    <a href=\"https://www.youtube.com/watch?v=dQRARRAhRLc\" class=\"no-tufte-underline\" title=\"Mariana BO (Tomorrowland Belgium 2019)\">\n      <img src=\"/image/yid-dQRARRAhRLc.jpg\" alt=\"Mariana BO (Tomorrowland Belgium 2019)\">\n    </a>\n    <figcaption>Mariana BO (Tomorrowland Belgium 2019)</figcaption>\n  </figure>\n  <p><a href=\"https://www.youtube.com/watch?v=dQRARRAhRLc\" title=\"Mariana BO (Tomorrowland Belgium 2019)\">Play Video</a></p>\n</div>\n<div class=\"section yt\">\n  <header>\n    <h2>Mariana BO: Shankara</h2>\n  </header>\n  <figure>\n    <a href=\"https://www.youtube.com/watch?v=V7-JQcNm8W0\" class=\"no-tufte-underline\" title=\"Mariana BO: Shankara\">\n      <img src=\"/image/yid-V7-JQcNm8W0.jpg\" alt=\"Mariana BO: Shankara\">\n    </a>\n    <figcaption>Mariana BO: Shankara</figcaption>\n  </figure>\n  <p><a href=\"https://www.youtube.com/watch?v=V7-JQcNm8W0\" title=\"Mariana BO: Shankara\">Play Video</a></p>\n</div>\n<div class=\"section\">\n  <header>\n    <h2>MATTN</h2>\n  </header>\n  <p><a href=\"https://www.youtube.com/channel/UCojmPu73tS_5hcxUOoCtHjw\">YouTube Topic</a></p>\n</div>\n<div class=\"section yt\">\n  <header>\n    <h2>MATTN (Tomorrowland Mainstage 2019)</h2>\n  </header>\n  <figure>\n    <a href=\"https://www.youtube.com/watch?v=ksqBDYwqkHA\" class=\"no-tufte-underline\" title=\"MATTN (Tomorrowland Mainstage 2019)\">\n      <img src=\"/image/yid-ksqBDYwqkHA.jpg\" alt=\"MATTN (Tomorrowland Mainstage 2019)\">\n    </a>\n    <figcaption>MATTN (Tomorrowland Mainstage 2019)</figcaption>\n  </figure>\n  <p><a href=\"https://www.youtube.com/watch?v=ksqBDYwqkHA\" title=\"MATTN (Tomorrowland Mainstage 2019)\">Play Video</a></p>\n</div>\n<div class=\"section yt\">\n  <header>\n    <h2>MATTN: Jungle Fever</h2>\n  </header>\n  <figure>\n    <a href=\"https://www.youtube.com/watch?v=F18eozyUKoM\" class=\"no-tufte-underline\" title=\"MATTN: Jungle Fever\">\n      <img src=\"/image/yid-F18eozyUKoM.jpg\" alt=\"MATTN: Jungle Fever\">\n    </a>\n    <figcaption>MATTN: Jungle Fever</figcaption>\n  </figure>\n  <p><a href=\"https://www.youtube.com/watch?v=F18eozyUKoM\" title=\"MATTN: Jungle Fever\">Play Video</a></p>\n</div>\n<div class=\"section\">\n  <header>\n    <h2>Peggy Gou</h2>\n  </header>\n  <p><a href=\"https://www.youtube.com/channel/UConl7T_sh6sQCwYe8WrQNbQ\">YouTube Topic</a></p>\n</div>\n<div class=\"section yt\">\n  <header>\n    <h2>Peggy Gou (Palais des Beaux-Arts de Lille for Cercle)</h2>\n  </header>\n  <figure>\n    <a href=\"https://www.youtube.com/watch?v=-UOMvxh4MYU\" class=\"no-tufte-underline\" title=\"Peggy Gou (Palais des Beaux-Arts de Lille for Cercle)\">\n      <img src=\"/image/yid--UOMvxh4MYU.jpg\" alt=\"Peggy Gou (Palais des Beaux-Arts de Lille for Cercle)\">\n    </a>\n    <figcaption>Peggy Gou (Palais des Beaux-Arts de Lille for Cercle)</figcaption>\n  </figure>\n  <p><a href=\"https://www.youtube.com/watch?v=-UOMvxh4MYU\" title=\"Peggy Gou (Palais des Beaux-Arts de Lille for Cercle)\">Play Video</a></p>\n</div>\n<div class=\"section yt\">\n  <header>\n    <h2>Peggy Gou: Starry Night</h2>\n  </header>\n  <figure>\n    <a href=\"https://www.youtube.com/watch?v=r_wwmmo6UGY\" class=\"no-tufte-underline\" title=\"Peggy Gou: Starry Night\">\n      <img src=\"/image/yid-r_wwmmo6UGY.jpg\" alt=\"Peggy Gou: Starry Night\">\n    </a>\n    <figcaption>Peggy Gou: Starry Night</figcaption>\n  </figure>\n  <p><a href=\"https://www.youtube.com/watch?v=r_wwmmo6UGY\" title=\"Peggy Gou: Starry Night\">Play Video</a></p>\n</div>\n<div class=\"section\">\n  <header>\n    <h2>Miss K8</h2>\n  </header>\n  <p><a href=\"https://www.youtube.com/channel/UC9QwEZj-KBlYzW3hbsgwS-Q\">YouTube Channel</a></p>\n</div>\n<div class=\"section yt\">\n  <header>\n    <h2>Miss K8 (Qlimax 2019)</h2>\n  </header>\n  <figure>\n    <a href=\"https://www.youtube.com/watch?v=Z0N1i7LwXXE\" class=\"no-tufte-underline\" title=\"Miss K8 (Qlimax 2019)\">\n      <img src=\"/image/yid-Z0N1i7LwXXE.jpg\" alt=\"Miss K8 (Qlimax 2019)\">\n    </a>\n    <figcaption>Miss K8 (Qlimax 2019)</figcaption>\n  </figure>\n  <p><a href=\"https://www.youtube.com/watch?v=Z0N1i7LwXXE\" title=\"Miss K8 (Qlimax 2019)\">Play Video</a></p>\n</div>\n<div class=\"section yt\">\n  <header>\n    <h2>Miss K8: Out Of The Frame</h2>\n  </header>\n  <figure>\n    <a href=\"https://www.youtube.com/watch?v=k9sC2RcFsQg\" class=\"no-tufte-underline\" title=\"Miss K8: Out Of The Frame\">\n      <img src=\"/image/yid-k9sC2RcFsQg.jpg\" alt=\"Miss K8: Out Of The Frame\">\n    </a>\n    <figcaption>Miss K8: Out Of The Frame</figcaption>\n  </figure>\n  <p><a href=\"https://www.youtube.com/watch?v=k9sC2RcFsQg\" title=\"Miss K8: Out Of The Frame\">Play Video</a></p>\n</div>\n<div class=\"section\">\n  <header>\n    <h2>Charlotte de Witte</h2>\n  </header>\n  <p><a href=\"https://www.youtube.com/channel/UC-yOW3e6zBSo1JwLXq46Suw\">YouTube Channel</a></p>\n</div>\n<div class=\"section yt\">\n  <header>\n    <h2>Charlotte de Witte (Dour Festival 2017)</h2>\n  </header>\n  <figure>\n    <a href=\"https://www.youtube.com/watch?v=AtZxg-OC5ho\" class=\"no-tufte-underline\" title=\"Charlotte de Witte (Dour Festival 2017)\">\n      <img src=\"/image/yid-AtZxg-OC5ho.jpg\" alt=\"Charlotte de Witte (Dour Festival 2017)\">\n    </a>\n    <figcaption>Charlotte de Witte (Dour Festival 2017)</figcaption>\n  </figure>\n  <p><a href=\"https://www.youtube.com/watch?v=AtZxg-OC5ho\" title=\"Charlotte de Witte (Dour Festival 2017)\">Play Video</a></p>\n</div>\n<div class=\"section yt\">\n  <header>\n    <h2>Charlotte de Witte: Time</h2>\n  </header>\n  <figure>\n    <a href=\"https://www.youtube.com/watch?v=qNWQ5TGujVI\" class=\"no-tufte-underline\" title=\"Charlotte de Witte: Time\">\n      <img src=\"/image/yid-qNWQ5TGujVI.jpg\" alt=\"Charlotte de Witte: Time\">\n    </a>\n    <figcaption>Charlotte de Witte: Time</figcaption>\n  </figure>\n  <p><a href=\"https://www.youtube.com/watch?v=qNWQ5TGujVI\" title=\"Charlotte de Witte: Time\">Play Video</a></p>\n</div>\n<div class=\"section\">\n  <header>\n    <h2>NERVO</h2>\n  </header>\n  <p><a href=\"https://www.youtube.com/channel/UCPIq_wSB6DYBtoee4KqSZnw\">YouTube Channel</a></p>\n</div>\n<div class=\"section yt\">\n  <header>\n    <h2>NERVO (Tomorrowland July 22, 2017)</h2>\n  </header>\n  <figure>\n    <a href=\"https://www.youtube.com/watch?v=_m9OgQkdVqQ\" class=\"no-tufte-underline\" title=\"NERVO (Tomorrowland July 22, 2017)\">\n      <img src=\"/image/yid-_m9OgQkdVqQ.jpg\" alt=\"NERVO (Tomorrowland July 22, 2017)\">\n    </a>\n    <figcaption>NERVO (Tomorrowland July 22, 2017)</figcaption>\n  </figure>\n  <p><a href=\"https://www.youtube.com/watch?v=_m9OgQkdVqQ\" title=\"NERVO (Tomorrowland July 22, 2017)\">Play Video</a></p>\n</div>\n<div class=\"section yt\">\n  <header>\n    <h2>NERVO: The Way We See The World</h2>\n  </header>\n  <figure>\n    <a href=\"https://www.youtube.com/watch?v=rTOMpaOd31g\" class=\"no-tufte-underline\" title=\"NERVO: The Way We See The World\">\n      <img src=\"/image/yid-rTOMpaOd31g.jpg\" alt=\"NERVO: The Way We See The World\">\n    </a>\n    <figcaption>NERVO: The Way We See The World</figcaption>\n  </figure>\n  <p><a href=\"https://www.youtube.com/watch?v=rTOMpaOd31g\" title=\"NERVO: The Way We See The World\">Play Video</a></p>\n</div>\n<div class=\"section\">\n  <header>\n    <h2>Alison Wonderland</h2>\n  </header>\n  <p><a href=\"https://www.youtube.com/channel/UCB6R4ceqzkFiNX6FjDNzuKw\">YouTube Channel</a></p>\n</div>\n<div class=\"section yt\">\n  <header>\n    <h2>Alison Wonderland (The Lab LA)</h2>\n  </header>\n  <figure>\n    <a href=\"https://www.youtube.com/watch?v=HIXwkduDI3w\" class=\"no-tufte-underline\" title=\"Alison Wonderland (The Lab LA)\">\n      <img src=\"/image/yid-HIXwkduDI3w.jpg\" alt=\"Alison Wonderland (The Lab LA)\">\n    </a>\n    <figcaption>Alison Wonderland (The Lab LA)</figcaption>\n  </figure>\n  <p><a href=\"https://www.youtube.com/watch?v=HIXwkduDI3w\" title=\"Alison Wonderland (The Lab LA)\">Play Video</a></p>\n</div>\n<div class=\"section yt\">\n  <header>\n    <h2>Alison Wonderland: Peace</h2>\n  </header>\n  <figure>\n    <a href=\"https://www.youtube.com/watch?v=KbGV1KEXds4\" class=\"no-tufte-underline\" title=\"Alison Wonderland: Peace\">\n      <img src=\"/image/yid-KbGV1KEXds4.jpg\" alt=\"Alison Wonderland: Peace\">\n    </a>\n    <figcaption>Alison Wonderland: Peace</figcaption>\n  </figure>\n  <p><a href=\"https://www.youtube.com/watch?v=KbGV1KEXds4\" title=\"Alison Wonderland: Peace\">Play Video</a></p>\n</div>\n<div class=\"section\">\n  <header>\n    <h2>Nina Kraviz</h2>\n  </header>\n  <p><a href=\"https://www.youtube.com/channel/UCF6lav85ybIK3Umon9oI-dw\">YouTube Topic</a></p>\n</div>\n<div class=\"section yt\">\n  <header>\n    <h2>Nina Kraviz (Tour Eiffel for Cercle)</h2>\n  </header>\n  <figure>\n    <a href=\"https://www.youtube.com/watch?v=oFvqo1dil7M\" class=\"no-tufte-underline\" title=\"Nina Kraviz (Tour Eiffel for Cercle)\">\n      <img src=\"/image/yid-oFvqo1dil7M.jpg\" alt=\"Nina Kraviz (Tour Eiffel for Cercle)\">\n    </a>\n    <figcaption>Nina Kraviz (Tour Eiffel for Cercle)</figcaption>\n  </figure>\n  <p><a href=\"https://www.youtube.com/watch?v=oFvqo1dil7M\" title=\"Nina Kraviz (Tour Eiffel for Cercle)\">Play Video</a></p>\n</div>\n<div class=\"section yt\">\n  <header>\n    <h2>Nina Kraviz: Dream Machine</h2>\n  </header>\n  <figure>\n    <a href=\"https://www.youtube.com/watch?v=JDJRg8sowP4\" class=\"no-tufte-underline\" title=\"Nina Kraviz: Dream Machine\">\n      <img src=\"/image/yid-JDJRg8sowP4.jpg\" alt=\"Nina Kraviz: Dream Machine\">\n    </a>\n    <figcaption>Nina Kraviz: Dream Machine</figcaption>\n  </figure>\n  <p><a href=\"https://www.youtube.com/watch?v=JDJRg8sowP4\" title=\"Nina Kraviz: Dream Machine\">Play Video</a></p>\n</div>",
  "print": "<div class=\"section yt avoid-break-inside\" style=\"padding-bottom: 2rem;\">\n  <span>How To DJ For Beginners | Alison Wonderland<sup>[1]</sup></span>\n</div>\n<div class=\"section avoid-break-inside\" style=\"padding-bottom: 2rem;\">\n  <header>\n    <h2>Mariana BO</h2>\n  </header>\n  <div class=\"paragraph\"><span>YouTube Channel<sup>[2]</sup></span> / <span>YouTube Topic<sup>[3]</sup></span></div>\n</div>\n<div class=\"section yt avoid-break-inside\" style=\"padding-bottom: 2rem;\">\n  <span>Mariana BO (Tomorrowland Belgium 2019)<sup>[4]</sup></span>\n</div>\n<div class=\"section yt avoid-break-inside\" style=\"padding-bottom: 2rem;\">\n  <span>Mariana BO: Shankara<sup>[5]</sup></span>\n</div>\n<div class=\"section avoid-break-inside\" style=\"padding-bottom: 2rem;\">\n  <header>\n    <h2>MATTN</h2>\n  </header>\n  <div class=\"paragraph\"><span>YouTube Topic<sup>[6]</sup></span></div>\n</div>\n<div class=\"section yt avoid-break-inside\" style=\"padding-bottom: 2rem;\">\n  <span>MATTN (Tomorrowland Mainstage 2019)<sup>[7]</sup></span>\n</div>\n<div class=\"section yt avoid-break-inside\" style=\"padding-bottom: 2rem;\">\n  <span>MATTN: Jungle Fever<sup>[8]</sup></span>\n</div>\n<div class=\"section avoid-break-inside\" style=\"padding-bottom: 2rem;\">\n  <header>\n    <h2>Peggy Gou</h2>\n  </header>\n  <div class=\"paragraph\"><span>YouTube Topic<sup>[9]</sup></span></div>\n</div>\n<div class=\"section yt avoid-break-inside\" style=\"padding-bottom: 2rem;\">\n  <span>Peggy Gou (Palais des Beaux-Arts de Lille for Cercle)<sup>[10]</sup></span>\n</div>\n<div class=\"section yt avoid-break-inside\" style=\"padding-bottom: 2rem;\">\n  <span>Peggy Gou: Starry Night<sup>[11]</sup></span>\n</div>\n<div class=\"section avoid-break-inside\" style=\"padding-bottom: 2rem;\">\n  <header>\n    <h2>Miss K8</h2>\n  </header>\n  <div class=\"paragraph\"><span>YouTube Channel<sup>[12]</sup></span></div>\n</div>\n<div class=\"section yt avoid-break-inside\" style=\"padding-bottom: 2rem;\">\n  <span>Miss K8 (Qlimax 2019)<sup>[13]</sup></span>\n</div>\n<div class=\"section yt avoid-break-inside\" style=\"padding-bottom: 2rem;\">\n  <span>Miss K8: Out Of The Frame<sup>[14]</sup></span>\n</div>\n<div class=\"section avoid-break-inside\" style=\"padding-bottom: 2rem;\">\n  <header>\n    <h2>Charlotte de Witte</h2>\n  </header>\n  <div class=\"paragraph\"><span>YouTube Channel<sup>[15]</sup></span></div>\n</div>\n<div class=\"section yt avoid-break-inside\" style=\"padding-bottom: 2rem;\">\n  <span>Charlotte de Witte (Dour Festival 2017)<sup>[16]</sup></span>\n</div>\n<div class=\"section yt avoid-break-inside\" style=\"padding-bottom: 2rem;\">\n  <span>Charlotte de Witte: Time<sup>[17]</sup></span>\n</div>\n<div class=\"section avoid-break-inside\" style=\"padding-bottom: 2rem;\">\n  <header>\n    <h2>NERVO</h2>\n  </header>\n  <div class=\"paragraph\"><span>YouTube Channel<sup>[18]</sup></span></div>\n</div>\n<div class=\"section yt avoid-break-inside\" style=\"padding-bottom: 2rem;\">\n  <span>NERVO (Tomorrowland July 22, 2017)<sup>[19]</sup></span>\n</div>\n<div class=\"section yt avoid-break-inside\" style=\"padding-bottom: 2rem;\">\n  <span>NERVO: The Way We See The World<sup>[20]</sup></span>\n</div>\n<div class=\"section avoid-break-inside\" style=\"padding-bottom: 2rem;\">\n  <header>\n    <h2>Alison Wonderland</h2>\n  </header>\n  <div class=\"paragraph\"><span>YouTube Channel<sup>[21]</sup></span></div>\n</div>\n<div class=\"section yt avoid-break-inside\" style=\"padding-bottom: 2rem;\">\n  <span>Alison Wonderland (The Lab LA)<sup>[22]</sup></span>\n</div>\n<div class=\"section yt avoid-break-inside\" style=\"padding-bottom: 2rem;\">\n  <span>Alison Wonderland: Peace<sup>[23]</sup></span>\n</div>\n<div class=\"section avoid-break-inside\" style=\"padding-bottom: 2rem;\">\n  <header>\n    <h2>Nina Kraviz</h2>\n  </header>\n  <div class=\"paragraph\"><span>YouTube Topic<sup>[24]</sup></span></div>\n</div>\n<div class=\"section yt avoid-break-inside\" style=\"padding-bottom: 2rem;\">\n  <span>Nina Kraviz (Tour Eiffel for Cercle)<sup>[25]</sup></span>\n</div>\n<div class=\"section yt avoid-break-inside\" style=\"padding-bottom: 2rem;\">\n  <span>Nina Kraviz: Dream Machine<sup>[26]</sup></span>\n</div>\n<div class=\"break-after\">&nbsp;</div>\n<div>\n  <div class=\"section\" style=\"padding-bottom: 1rem;\">References</div>\n  <div>[1]: https://www.youtube.com/watch?v=rzg8OPPKVdM</div>\n  <div>[2]: https://www.youtube.com/channel/UCXBxS3vJZmrKUTOmjG0XnKQ</div>\n  <div>[3]: https://www.youtube.com/channel/UC7orAmV1JD-j-cIxOW7gi3w</div>\n  <div>[4]: https://www.youtube.com/watch?v=dQRARRAhRLc</div>\n  <div>[5]: https://www.youtube.com/watch?v=V7-JQcNm8W0</div>\n  <div>[6]: https://www.youtube.com/channel/UCojmPu73tS_5hcxUOoCtHjw</div>\n  <div>[7]: https://www.youtube.com/watch?v=ksqBDYwqkHA</div>\n  <div>[8]: https://www.youtube.com/watch?v=F18eozyUKoM</div>\n  <div>[9]: https://www.youtube.com/channel/UConl7T_sh6sQCwYe8WrQNbQ</div>\n  <div>[10]: https://www.youtube.com/watch?v=-UOMvxh4MYU</div>\n  <div>[11]: https://www.youtube.com/watch?v=r_wwmmo6UGY</div>\n  <div>[12]: https://www.youtube.com/channel/UC9QwEZj-KBlYzW3hbsgwS-Q</div>\n  <div>[13]: https://www.youtube.com/watch?v=Z0N1i7LwXXE</div>\n  <div>[14]: https://www.youtube.com/watch?v=k9sC2RcFsQg</div>\n  <div>[15]: https://www.youtube.com/channel/UC-yOW3e6zBSo1JwLXq46Suw</div>\n  <div>[16]: https://www.youtube.com/watch?v=AtZxg-OC5ho</div>\n  <div>[17]: https://www.youtube.com/watch?v=qNWQ5TGujVI</div>\n  <div>[18]: https://www.youtube.com/channel/UCPIq_wSB6DYBtoee4KqSZnw</div>\n  <div>[19]: https://www.youtube.com/watch?v=_m9OgQkdVqQ</div>\n  <div>[20]: https://www.youtube.com/watch?v=rTOMpaOd31g</div>\n  <div>[21]: https://www.youtube.com/channel/UCB6R4ceqzkFiNX6FjDNzuKw</div>\n  <div>[22]: https://www.youtube.com/watch?v=HIXwkduDI3w</div>\n  <div>[23]: https://www.youtube.com/watch?v=KbGV1KEXds4</div>\n  <div>[24]: https://www.youtube.com/channel/UCF6lav85ybIK3Umon9oI-dw</div>\n  <div>[25]: https://www.youtube.com/watch?v=oFvqo1dil7M</div>\n  <div>[26]: https://www.youtube.com/watch?v=JDJRg8sowP4</div>\n</div>",
  "bootstrap": "<div class=\"card card-section bg-dark text-warning shadow\">\n  <div class=\"card-header\">How To DJ For Beginners | Alison Wonderland</div>\n  <a href=\"https://www.youtube.com/watch?v=rzg8OPPKVdM\" title=\"How To DJ For Beginners | Alison Wonderland\" alt=\"How To DJ For Beginners | Alison Wonderland\"><img src=\"/image/yid-rzg8OPPKVdM.jpg\" alt=\"How To DJ For Beginners | Alison Wonderland\" class=\"card-img\"></a>\n  <div class=\"card-body\">\n    <a href=\"https://www.youtube.com/watch?v=rzg8OPPKVdM\" title=\"How To DJ For Beginners | Alison Wonderland\" class=\"btn btn-warning\">Play Video</a>\n  </div>\n</div>\n<div class=\"card card-section bg-dark text-warning shadow\">\n  <div class=\"card-body\">\n    <h5 class=\"card-title\">Mariana BO</h5>\n    <div class=\"card-text\">\n      <p><a href=\"https://www.youtube.com/channel/UCXBxS3vJZmrKUTOmjG0XnKQ\">YouTube Channel</a> / <a href=\"https://www.youtube.com/channel/UC7orAmV1JD-j-cIxOW7gi3w\">YouTube Topic</a></p>\n    </div>\n  </div>\n</div>\n<div class=\"card card-section bg-dark text-warning shadow\">\n  <div class=\"card-header\">Mariana BO (Tomorrowland Belgium 2019)</div>\n  <a href=\"https://www.youtube.com/watch?v=dQRARRAhRLc\" title=\"Mariana BO (Tomorrowland Belgium 2019)\" alt=\"Mariana BO (Tomorrowland Belgium 2019)\"><img src=\"/image/yid-dQRARRAhRLc.jpg\" alt=\"Mariana BO (Tomorrowland Belgium 2019)\" class=\"card-img\"></a>\n  <div class=\"card-body\">\n    <a href=\"https://www.youtube.com/watch?v=dQRARRAhRLc\" title=\"Mariana BO (Tomorrowland Belgium 2019)\" class=\"btn btn-warning\">Play Video</a>\n  </div>\n</div>\n<div class=\"card card-section bg-dark text-warning shadow\">\n  <div class=\"card-header\">Mariana BO: Shankara</div>\n  <a href=\"https://www.youtube.com/watch?v=V7-JQcNm8W0\" title=\"Mariana BO: Shankara\" alt=\"Mariana BO: Shankara\"><img src=\"/image/yid-V7-JQcNm8W0.jpg\" alt=\"Mariana BO: Shankara\" class=\"card-img\"></a>\n  <div class=\"card-body\">\n    <a href=\"https://www.youtube.com/watch?v=V7-JQcNm8W0\" title=\"Mariana BO: Shankara\" class=\"btn btn-warning\">Play Video</a>\n  </div>\n</div>\n<div class=\"card card-section bg-dark text-warning shadow\">\n  <div class=\"card-body\">\n    <h5 class=\"card-title\">MATTN</h5>\n    <div class=\"card-text\">\n      <p><a href=\"https://www.youtube.com/channel/UCojmPu73tS_5hcxUOoCtHjw\">YouTube Topic</a></p>\n    </div>\n  </div>\n</div>\n<div class=\"card card-section bg-dark text-warning shadow\">\n  <div class=\"card-header\">MATTN (Tomorrowland Mainstage 2019)</div>\n  <a href=\"https://www.youtube.com/watch?v=ksqBDYwqkHA\" title=\"MATTN (Tomorrowland Mainstage 2019)\" alt=\"MATTN (Tomorrowland Mainstage 2019)\"><img src=\"/image/yid-ksqBDYwqkHA.jpg\" alt=\"MATTN (Tomorrowland Mainstage 2019)\" class=\"card-img\"></a>\n  <div class=\"card-body\">\n    <a href=\"https://www.youtube.com/watch?v=ksqBDYwqkHA\" title=\"MATTN (Tomorrowland Mainstage 2019)\" class=\"btn btn-warning\">Play Video</a>\n  </div>\n</div>\n<div class=\"card card-section bg-dark text-warning shadow\">\n  <div class=\"card-header\">MATTN: Jungle Fever</div>\n  <a href=\"https://www.youtube.com/watch?v=F18eozyUKoM\" title=\"MATTN: Jungle Fever\" alt=\"MATTN: Jungle Fever\"><img src=\"/image/yid-F18eozyUKoM.jpg\" alt=\"MATTN: Jungle Fever\" class=\"card-img\"></a>\n  <div class=\"card-body\">\n    <a href=\"https://www.youtube.com/watch?v=F18eozyUKoM\" title=\"MATTN: Jungle Fever\" class=\"btn btn-warning\">Play Video</a>\n  </div>\n</div>\n<div class=\"card card-section bg-dark text-warning shadow\">\n  <div class=\"card-body\">\n    <h5 class=\"card-title\">Peggy Gou</h5>\n    <div class=\"card-text\">\n      <p><a href=\"https://www.youtube.com/channel/UConl7T_sh6sQCwYe8WrQNbQ\">YouTube Topic</a></p>\n    </div>\n  </div>\n</div>\n<div class=\"card card-section bg-dark text-warning shadow\">\n  <div class=\"card-header\">Peggy Gou (Palais des Beaux-Arts de Lille for Cercle)</div>\n  <a href=\"https://www.youtube.com/watch?v=-UOMvxh4MYU\" title=\"Peggy Gou (Palais des Beaux-Arts de Lille for Cercle)\" alt=\"Peggy Gou (Palais des Beaux-Arts de Lille for Cercle)\"><img src=\"/image/yid--UOMvxh4MYU.jpg\" alt=\"Peggy Gou (Palais des Beaux-Arts de Lille for Cercle)\" class=\"card-img\"></a>\n  <div class=\"card-body\">\n    <a href=\"https://www.youtube.com/watch?v=-UOMvxh4MYU\" title=\"Peggy Gou (Palais des Beaux-Arts de Lille for Cercle)\" class=\"btn btn-warning\">Play Video</a>\n  </div>\n</div>\n<div class=\"card card-section bg-dark text-warning shadow\">\n  <div class=\"card-header\">Peggy Gou: Starry Night</div>\n  <a href=\"https://www.youtube.com/watch?v=r_wwmmo6UGY\" title=\"Peggy Gou: Starry Night\" alt=\"Peggy Gou: Starry Night\"><img src=\"/image/yid-r_wwmmo6UGY.jpg\" alt=\"Peggy Gou: Starry Night\" class=\"card-img\"></a>\n  <div class=\"card-body\">\n    <a href=\"https://www.youtube.com/watch?v=r_wwmmo6UGY\" title=\"Peggy Gou: Starry Night\" class=\"btn btn-warning\">Play Video</a>\n  </div>\n</div>\n<div class=\"card card-section bg-dark text-warning shadow\">\n  <div class=\"card-body\">\n    <h5 class=\"card-title\">Miss K8</h5>\n    <div class=\"card-text\">\n      <p><a href=\"https://www.youtube.com/channel/UC9QwEZj-KBlYzW3hbsgwS-Q\">YouTube Channel</a></p>\n    </div>\n  </div>\n</div>\n<div class=\"card card-section bg-dark text-warning shadow\">\n  <div class=\"card-header\">Miss K8 (Qlimax 2019)</div>\n  <a href=\"https://www.youtube.com/watch?v=Z0N1i7LwXXE\" title=\"Miss K8 (Qlimax 2019)\" alt=\"Miss K8 (Qlimax 2019)\"><img src=\"/image/yid-Z0N1i7LwXXE.jpg\" alt=\"Miss K8 (Qlimax 2019)\" class=\"card-img\"></a>\n  <div class=\"card-body\">\n    <a href=\"https://www.youtube.com/watch?v=Z0N1i7LwXXE\" title=\"Miss K8 (Qlimax 2019)\" class=\"btn btn-warning\">Play Video</a>\n  </div>\n</div>\n<div class=\"card card-section bg-dark text-warning shadow\">\n  <div class=\"card-header\">Miss K8: Out Of The Frame</div>\n  <a href=\"https://www.youtube.com/watch?v=k9sC2RcFsQg\" title=\"Miss K8: Out Of The Frame\" alt=\"Miss K8: Out Of The Frame\"><img src=\"/image/yid-k9sC2RcFsQg.jpg\" alt=\"Miss K8: Out Of The Frame\" class=\"card-img\"></a>\n  <div class=\"card-body\">\n    <a href=\"https://www.youtube.com/watch?v=k9sC2RcFsQg\" title=\"Miss K8: Out Of The Frame\" class=\"btn btn-warning\">Play Video</a>\n  </div>\n</div>\n<div class=\"card card-section bg-dark text-warning shadow\">\n  <div class=\"card-body\">\n    <h5 class=\"card-title\">Charlotte de Witte</h5>\n    <div class=\"card-text\">\n      <p><a href=\"https://www.youtube.com/channel/UC-yOW3e6zBSo1JwLXq46Suw\">YouTube Channel</a></p>\n    </div>\n  </div>\n</div>\n<div class=\"card card-section bg-dark text-warning shadow\">\n  <div class=\"card-header\">Charlotte de Witte (Dour Festival 2017)</div>\n  <a href=\"https://www.youtube.com/watch?v=AtZxg-OC5ho\" title=\"Charlotte de Witte (Dour Festival 2017)\" alt=\"Charlotte de Witte (Dour Festival 2017)\"><img src=\"/image/yid-AtZxg-OC5ho.jpg\" alt=\"Charlotte de Witte (Dour Festival 2017)\" class=\"card-img\"></a>\n  <div class=\"card-body\">\n    <a href=\"https://www.youtube.com/watch?v=AtZxg-OC5ho\" title=\"Charlotte de Witte (Dour Festival 2017)\" class=\"btn btn-warning\">Play Video</a>\n  </div>\n</div>\n<div class=\"card card-section bg-dark text-warning shadow\">\n  <div class=\"card-header\">Charlotte de Witte: Time</div>\n  <a href=\"https://www.youtube.com/watch?v=qNWQ5TGujVI\" title=\"Charlotte de Witte: Time\" alt=\"Charlotte de Witte: Time\"><img src=\"/image/yid-qNWQ5TGujVI.jpg\" alt=\"Charlotte de Witte: Time\" class=\"card-img\"></a>\n  <div class=\"card-body\">\n    <a href=\"https://www.youtube.com/watch?v=qNWQ5TGujVI\" title=\"Charlotte de Witte: Time\" class=\"btn btn-warning\">Play Video</a>\n  </div>\n</div>\n<div class=\"card card-section bg-dark text-warning shadow\">\n  <div class=\"card-body\">\n    <h5 class=\"card-title\">NERVO</h5>\n    <div class=\"card-text\">\n      <p><a href=\"https://www.youtube.com/channel/UCPIq_wSB6DYBtoee4KqSZnw\">YouTube Channel</a></p>\n    </div>\n  </div>\n</div>\n<div class=\"card card-section bg-dark text-warning shadow\">\n  <div class=\"card-header\">NERVO (Tomorrowland July 22, 2017)</div>\n  <a href=\"https://www.youtube.com/watch?v=_m9OgQkdVqQ\" title=\"NERVO (Tomorrowland July 22, 2017)\" alt=\"NERVO (Tomorrowland July 22, 2017)\"><img src=\"/image/yid-_m9OgQkdVqQ.jpg\" alt=\"NERVO (Tomorrowland July 22, 2017)\" class=\"card-img\"></a>\n  <div class=\"card-body\">\n    <a href=\"https://www.youtube.com/watch?v=_m9OgQkdVqQ\" title=\"NERVO (Tomorrowland July 22, 2017)\" class=\"btn btn-warning\">Play Video</a>\n  </div>\n</div>\n<div class=\"card card-section bg-dark text-warning shadow\">\n  <div class=\"card-header\">NERVO: The Way We See The World</div>\n  <a href=\"https://www.youtube.com/watch?v=rTOMpaOd31g\" title=\"NERVO: The Way We See The World\" alt=\"NERVO: The Way We See The World\"><img src=\"/image/yid-rTOMpaOd31g.jpg\" alt=\"NERVO: The Way We See The World\" class=\"card-img\"></a>\n  <div class=\"card-body\">\n    <a href=\"https://www.youtube.com/watch?v=rTOMpaOd31g\" title=\"NERVO: The Way We See The World\" class=\"btn btn-warning\">Play Video</a>\n  </div>\n</div>\n<div class=\"card card-section bg-dark text-warning shadow\">\n  <div class=\"card-body\">\n    <h5 class=\"card-title\">Alison Wonderland</h5>\n    <div class=\"card-text\">\n      <p><a href=\"https://www.youtube.com/channel/UCB6R4ceqzkFiNX6FjDNzuKw\">YouTube Channel</a></p>\n    </div>\n  </div>\n</div>\n<div class=\"card card-section bg-dark text-warning shadow\">\n  <div class=\"card-header\">Alison Wonderland (The Lab LA)</div>\n  <a href=\"https://www.youtube.com/watch?v=HIXwkduDI3w\" title=\"Alison Wonderland (The Lab LA)\" alt=\"Alison Wonderland (The Lab LA)\"><img src=\"/image/yid-HIXwkduDI3w.jpg\" alt=\"Alison Wonderland (The Lab LA)\" class=\"card-img\"></a>\n  <div class=\"card-body\">\n    <a href=\"https://www.youtube.com/watch?v=HIXwkduDI3w\" title=\"Alison Wonderland (The Lab LA)\" class=\"btn btn-warning\">Play Video</a>\n  </div>\n</div>\n<div class=\"card card-section bg-dark text-warning shadow\">\n  <div class=\"card-header\">Alison Wonderland: Peace</div>\n  <a href=\"https://www.youtube.com/watch?v=KbGV1KEXds4\" title=\"Alison Wonderland: Peace\" alt=\"Alison Wonderland: Peace\"><img src=\"/image/yid-KbGV1KEXds4.jpg\" alt=\"Alison Wonderland: Peace\" class=\"card-img\"></a>\n  <div class=\"card-body\">\n    <a href=\"https://www.youtube.com/watch?v=KbGV1KEXds4\" title=\"Alison Wonderland: Peace\" class=\"btn btn-warning\">Play Video</a>\n  </div>\n</div>\n<div class=\"card card-section bg-dark text-warning shadow\">\n  <div class=\"card-body\">\n    <h5 class=\"card-title\">Nina Kraviz</h5>\n    <div class=\"card-text\">\n      <p><a href=\"https://www.youtube.com/channel/UCF6lav85ybIK3Umon9oI-dw\">YouTube Topic</a></p>\n    </div>\n  </div>\n</div>\n<div class=\"card card-section bg-dark text-warning shadow\">\n  <div class=\"card-header\">Nina Kraviz (Tour Eiffel for Cercle)</div>\n  <a href=\"https://www.youtube.com/watch?v=oFvqo1dil7M\" title=\"Nina Kraviz (Tour Eiffel for Cercle)\" alt=\"Nina Kraviz (Tour Eiffel for Cercle)\"><img src=\"/image/yid-oFvqo1dil7M.jpg\" alt=\"Nina Kraviz (Tour Eiffel for Cercle)\" class=\"card-img\"></a>\n  <div class=\"card-body\">\n    <a href=\"https://www.youtube.com/watch?v=oFvqo1dil7M\" title=\"Nina Kraviz (Tour Eiffel for Cercle)\" class=\"btn btn-warning\">Play Video</a>\n  </div>\n</div>\n<div class=\"card card-section bg-dark text-warning shadow\">\n  <div class=\"card-header\">Nina Kraviz: Dream Machine</div>\n  <a href=\"https://www.youtube.com/watch?v=JDJRg8sowP4\" title=\"Nina Kraviz: Dream Machine\" alt=\"Nina Kraviz: Dream Machine\"><img src=\"/image/yid-JDJRg8sowP4.jpg\" alt=\"Nina Kraviz: Dream Machine\" class=\"card-img\"></a>\n  <div class=\"card-body\">\n    <a href=\"https://www.youtube.com/watch?v=JDJRg8sowP4\" title=\"Nina Kraviz: Dream Machine\" class=\"btn btn-warning\">Play Video</a>\n  </div>\n</div>",
  "text": "How To DJ For Beginners | Alison Wonderland[1]\n\nMARIANA BO\n\nYouTube Channel[2] / YouTube Topic[3]\nMariana BO (Tomorrowland Belgium 2019)[4]\nMariana BO: Shankara[5]\n\nMATTN\n\nYouTube Topic[6]\nMATTN (Tomorrowland Mainstage 2019)[7]\nMATTN: Jungle Fever[8]\n\nPEGGY GOU\n\nYouTube Topic[9]\nPeggy Gou (Palais des Beaux-Arts de Lille for Cercle)[10]\nPeggy Gou: Starry Night[11]\n\nMISS K8\n\nYouTube Channel[12]\nMiss K8 (Qlimax 2019)[13]\nMiss K8: Out Of The Frame[14]\n\nCHARLOTTE DE WITTE\n\nYouTube Channel[15]\nCharlotte de Witte (Dour Festival 2017)[16]\nCharlotte de Witte: Time[17]\n\nNERVO\n\nYouTube Channel[18]\nNERVO (Tomorrowland July 22, 2017)[19]\nNERVO: The Way We See The World[20]\n\nALISON WONDERLAND\n\nYouTube Channel[21]\nAlison Wonderland (The Lab LA)[22]\nAlison Wonderland: Peace[23]\n\nNINA KRAVIZ\n\nYouTube Topic[24]\nNina Kraviz (Tour Eiffel for Cercle)[25]\nNina Kraviz: Dream Machine[26]\n \nReferences\n[1]: https://www.youtube.com/watch?v=rzg8OPPKVdM\n[2]: https://www.youtube.com/channel/UCXBxS3vJZmrKUTOmjG0XnKQ\n[3]: https://www.youtube.com/channel/UC7orAmV1JD-j-cIxOW7gi3w\n[4]: https://www.youtube.com/watch?v=dQRARRAhRLc\n[5]: https://www.youtube.com/watch?v=V7-JQcNm8W0\n[6]: https://www.youtube.com/channel/UCojmPu73tS_5hcxUOoCtHjw\n[7]: https://www.youtube.com/watch?v=ksqBDYwqkHA\n[8]: https://www.youtube.com/watch?v=F18eozyUKoM\n[9]: https://www.youtube.com/channel/UConl7T_sh6sQCwYe8WrQNbQ\n[10]: https://www.youtube.com/watch?v=-UOMvxh4MYU\n[11]: https://www.youtube.com/watch?v=r_wwmmo6UGY\n[12]: https://www.youtube.com/channel/UC9QwEZj-KBlYzW3hbsgwS-Q\n[13]: https://www.youtube.com/watch?v=Z0N1i7LwXXE\n[14]: https://www.youtube.com/watch?v=k9sC2RcFsQg\n[15]: https://www.youtube.com/channel/UC-yOW3e6zBSo1JwLXq46Suw\n[16]: https://www.youtube.com/watch?v=AtZxg-OC5ho\n[17]: https://www.youtube.com/watch?v=qNWQ5TGujVI\n[18]: https://www.youtube.com/channel/UCPIq_wSB6DYBtoee4KqSZnw\n[19]: https://www.youtube.com/watch?v=_m9OgQkdVqQ\n[20]: https://www.youtube.com/watch?v=rTOMpaOd31g\n[21]: https://www.youtube.com/channel/UCB6R4ceqzkFiNX6FjDNzuKw\n[22]: https://www.youtube.com/watch?v=HIXwkduDI3w\n[23]: https://www.youtube.com/watch?v=KbGV1KEXds4\n[24]: https://www.youtube.com/channel/UCF6lav85ybIK3Umon9oI-dw\n[25]: https://www.youtube.com/watch?v=oFvqo1dil7M\n[26]: https://www.youtube.com/watch?v=JDJRg8sowP4",
  "images": [
    {
      "title": "How To DJ For Beginners | Alison Wonderland",
      "url": "yid-rzg8OPPKVdM.jpg"
    },
    {
      "title": "Mariana BO (Tomorrowland Belgium 2019)",
      "url": "yid-dQRARRAhRLc.jpg"
    },
    {
      "title": "Mariana BO: Shankara",
      "url": "yid-V7-JQcNm8W0.jpg"
    },
    {
      "title": "MATTN (Tomorrowland Mainstage 2019)",
      "url": "yid-ksqBDYwqkHA.jpg"
    },
    {
      "title": "MATTN: Jungle Fever",
      "url": "yid-F18eozyUKoM.jpg"
    },
    {
      "title": "Peggy Gou (Palais des Beaux-Arts de Lille for Cercle)",
      "url": "yid--UOMvxh4MYU.jpg"
    },
    {
      "title": "Peggy Gou: Starry Night",
      "url": "yid-r_wwmmo6UGY.jpg"
    },
    {
      "title": "Miss K8 (Qlimax 2019)",
      "url": "yid-Z0N1i7LwXXE.jpg"
    },
    {
      "title": "Miss K8: Out Of The Frame",
      "url": "yid-k9sC2RcFsQg.jpg"
    },
    {
      "title": "Charlotte de Witte (Dour Festival 2017)",
      "url": "yid-AtZxg-OC5ho.jpg"
    },
    {
      "title": "Charlotte de Witte: Time",
      "url": "yid-qNWQ5TGujVI.jpg"
    },
    {
      "title": "NERVO (Tomorrowland July 22, 2017)",
      "url": "yid-_m9OgQkdVqQ.jpg"
    },
    {
      "title": "NERVO: The Way We See The World",
      "url": "yid-rTOMpaOd31g.jpg"
    },
    {
      "title": "Alison Wonderland (The Lab LA)",
      "url": "yid-HIXwkduDI3w.jpg"
    },
    {
      "title": "Alison Wonderland: Peace",
      "url": "yid-KbGV1KEXds4.jpg"
    },
    {
      "title": "Nina Kraviz (Tour Eiffel for Cercle)",
      "url": "yid-oFvqo1dil7M.jpg"
    },
    {
      "title": "Nina Kraviz: Dream Machine",
      "url": "yid-JDJRg8sowP4.jpg"
    }
  ],
  "links": [
    {
      "title": "How To DJ For Beginners | Alison Wonderland",
      "url": "https://www.youtube.com/watch?v=rzg8OPPKVdM",
      "hostname": "www.youtube.com"
    },
    {
      "title": "YouTube Channel",
      "url": "https://www.youtube.com/channel/UCXBxS3vJZmrKUTOmjG0XnKQ",
      "hostname": "www.youtube.com"
    },
    {
      "title": "YouTube Topic",
      "url": "https://www.youtube.com/channel/UC7orAmV1JD-j-cIxOW7gi3w",
      "hostname": "www.youtube.com"
    },
    {
      "title": "Mariana BO (Tomorrowland Belgium 2019)",
      "url": "https://www.youtube.com/watch?v=dQRARRAhRLc",
      "hostname": "www.youtube.com"
    },
    {
      "title": "Mariana BO: Shankara",
      "url": "https://www.youtube.com/watch?v=V7-JQcNm8W0",
      "hostname": "www.youtube.com"
    },
    {
      "title": "YouTube Topic",
      "url": "https://www.youtube.com/channel/UCojmPu73tS_5hcxUOoCtHjw",
      "hostname": "www.youtube.com"
    },
    {
      "title": "MATTN (Tomorrowland Mainstage 2019)",
      "url": "https://www.youtube.com/watch?v=ksqBDYwqkHA",
      "hostname": "www.youtube.com"
    },
    {
      "title": "MATTN: Jungle Fever",
      "url": "https://www.youtube.com/watch?v=F18eozyUKoM",
      "hostname": "www.youtube.com"
    },
    {
      "title": "YouTube Topic",
      "url": "https://www.youtube.com/channel/UConl7T_sh6sQCwYe8WrQNbQ",
      "hostname": "www.youtube.com"
    },
    {
      "title": "Peggy Gou (Palais des Beaux-Arts de Lille for Cercle)",
      "url": "https://www.youtube.com/watch?v=-UOMvxh4MYU",
      "hostname": "www.youtube.com"
    },
    {
      "title": "Peggy Gou: Starry Night",
      "url": "https://www.youtube.com/watch?v=r_wwmmo6UGY",
      "hostname": "www.youtube.com"
    },
    {
      "title": "YouTube Channel",
      "url": "https://www.youtube.com/channel/UC9QwEZj-KBlYzW3hbsgwS-Q",
      "hostname": "www.youtube.com"
    },
    {
      "title": "Miss K8 (Qlimax 2019)",
      "url": "https://www.youtube.com/watch?v=Z0N1i7LwXXE",
      "hostname": "www.youtube.com"
    },
    {
      "title": "Miss K8: Out Of The Frame",
      "url": "https://www.youtube.com/watch?v=k9sC2RcFsQg",
      "hostname": "www.youtube.com"
    },
    {
      "title": "YouTube Channel",
      "url": "https://www.youtube.com/channel/UC-yOW3e6zBSo1JwLXq46Suw",
      "hostname": "www.youtube.com"
    },
    {
      "title": "Charlotte de Witte (Dour Festival 2017)",
      "url": "https://www.youtube.com/watch?v=AtZxg-OC5ho",
      "hostname": "www.youtube.com"
    },
    {
      "title": "Charlotte de Witte: Time",
      "url": "https://www.youtube.com/watch?v=qNWQ5TGujVI",
      "hostname": "www.youtube.com"
    },
    {
      "title": "YouTube Channel",
      "url": "https://www.youtube.com/channel/UCPIq_wSB6DYBtoee4KqSZnw",
      "hostname": "www.youtube.com"
    },
    {
      "title": "NERVO (Tomorrowland July 22, 2017)",
      "url": "https://www.youtube.com/watch?v=_m9OgQkdVqQ",
      "hostname": "www.youtube.com"
    },
    {
      "title": "NERVO: The Way We See The World",
      "url": "https://www.youtube.com/watch?v=rTOMpaOd31g",
      "hostname": "www.youtube.com"
    },
    {
      "title": "YouTube Channel",
      "url": "https://www.youtube.com/channel/UCB6R4ceqzkFiNX6FjDNzuKw",
      "hostname": "www.youtube.com"
    },
    {
      "title": "Alison Wonderland (The Lab LA)",
      "url": "https://www.youtube.com/watch?v=HIXwkduDI3w",
      "hostname": "www.youtube.com"
    },
    {
      "title": "Alison Wonderland: Peace",
      "url": "https://www.youtube.com/watch?v=KbGV1KEXds4",
      "hostname": "www.youtube.com"
    },
    {
      "title": "YouTube Topic",
      "url": "https://www.youtube.com/channel/UCF6lav85ybIK3Umon9oI-dw",
      "hostname": "www.youtube.com"
    },
    {
      "title": "Nina Kraviz (Tour Eiffel for Cercle)",
      "url": "https://www.youtube.com/watch?v=oFvqo1dil7M",
      "hostname": "www.youtube.com"
    },
    {
      "title": "Nina Kraviz: Dream Machine",
      "url": "https://www.youtube.com/watch?v=JDJRg8sowP4",
      "hostname": "www.youtube.com"
    }
  ]
}